{"numTotalTestSuites":11,"numPassedTestSuites":2,"numFailedTestSuites":9,"numPendingTestSuites":0,"numTotalTests":160,"numPassedTests":117,"numFailedTests":43,"numPendingTests":0,"numTodoTests":0,"snapshot":{"added":0,"failure":false,"filesAdded":0,"filesRemoved":0,"filesRemovedList":[],"filesUnmatched":0,"filesUpdated":0,"matched":0,"total":0,"unchecked":0,"uncheckedKeysByFile":[],"unmatched":0,"updated":0,"didUpdate":false},"startTime":1773084906626,"success":false,"testResults":[{"assertionResults":[],"startTime":1773084906626,"endTime":1773084906626,"status":"failed","message":"Cannot find module './ex-04-operadores-aritmeticos.js' imported from '/home/vicmca/CodeProjects/School/materiais/atividades/2c-revisao-01/.ex.test.js'","name":"/home/vicmca/CodeProjects/School/materiais/atividades/2c-revisao-01/.ex.test.js"},{"assertionResults":[{"ancestorTitles":["Exercício 01"],"fullName":"Exercício 01 Ex01 - Válida - Questão 1","status":"passed","title":"Ex01 - Válida - Questão 1","duration":3.7193390000000477,"failureMessages":[],"meta":{}},{"ancestorTitles":["Exercício 01"],"fullName":"Exercício 01 Ex01 - Correta - Questão 1","status":"passed","title":"Ex01 - Correta - Questão 1","duration":0.7139640000000327,"failureMessages":[],"meta":{}},{"ancestorTitles":["Exercício 01"],"fullName":"Exercício 01 Ex01 - Válida - Questão 2","status":"passed","title":"Ex01 - Válida - Questão 2","duration":0.6198370000000182,"failureMessages":[],"meta":{}},{"ancestorTitles":["Exercício 01"],"fullName":"Exercício 01 Ex01 - Correta - Questão 2","status":"passed","title":"Ex01 - Correta - Questão 2","duration":0.9925380000000246,"failureMessages":[],"meta":{}},{"ancestorTitles":["Exercício 01"],"fullName":"Exercício 01 Ex01 - Válida - Questão 3","status":"passed","title":"Ex01 - Válida - Questão 3","duration":0.5673049999999762,"failureMessages":[],"meta":{}},{"ancestorTitles":["Exercício 01"],"fullName":"Exercício 01 Ex01 - Correta - Questão 3","status":"passed","title":"Ex01 - Correta - Questão 3","duration":0.3534000000000219,"failureMessages":[],"meta":{}},{"ancestorTitles":["Exercício 01"],"fullName":"Exercício 01 Ex01 - Válida - Questão 4","status":"passed","title":"Ex01 - Válida - Questão 4","duration":0.5961120000000051,"failureMessages":[],"meta":{}},{"ancestorTitles":["Exercício 01"],"fullName":"Exercício 01 Ex01 - Correta - Questão 4","status":"passed","title":"Ex01 - Correta - Questão 4","duration":0.5929950000000304,"failureMessages":[],"meta":{}},{"ancestorTitles":["Exercício 01"],"fullName":"Exercício 01 Ex01 - Válida - Questão 5","status":"passed","title":"Ex01 - Válida - Questão 5","duration":1.1656449999999836,"failureMessages":[],"meta":{}},{"ancestorTitles":["Exercício 01"],"fullName":"Exercício 01 Ex01 - Correta - Questão 5","status":"passed","title":"Ex01 - Correta - Questão 5","duration":0.5677430000000072,"failureMessages":[],"meta":{}},{"ancestorTitles":["Exercício 01"],"fullName":"Exercício 01 Ex01 - Válida - Questão 6","status":"passed","title":"Ex01 - Válida - Questão 6","duration":0.39479400000004716,"failureMessages":[],"meta":{}},{"ancestorTitles":["Exercício 01"],"fullName":"Exercício 01 Ex01 - Correta - Questão 6","status":"passed","title":"Ex01 - Correta - Questão 6","duration":0.2959380000000351,"failureMessages":[],"meta":{}},{"ancestorTitles":["Exercício 01"],"fullName":"Exercício 01 Ex01 - Válida - Questão 7","status":"passed","title":"Ex01 - Válida - Questão 7","duration":0.31193700000000035,"failureMessages":[],"meta":{}},{"ancestorTitles":["Exercício 01"],"fullName":"Exercício 01 Ex01 - Correta - Questão 7","status":"passed","title":"Ex01 - Correta - Questão 7","duration":0.2518709999999942,"failureMessages":[],"meta":{}},{"ancestorTitles":["Exercício 01"],"fullName":"Exercício 01 Ex01 - Válida - Questão 8","status":"failed","title":"Ex01 - Válida - Questão 8","duration":22.049279000000013,"failureMessages":["AssertionError: expected undefined to be type of 'boolean'\n    at /home/vicmca/CodeProjects/School/materiais/atividades/2c-revisao-01/ex01.test.js:24:30\n    at file:///home/vicmca/CodeProjects/School/materiais/atividades/2c-revisao-01/node_modules/@vitest/runner/dist/index.js:145:11\n    at file:///home/vicmca/CodeProjects/School/materiais/atividades/2c-revisao-01/node_modules/@vitest/runner/dist/index.js:915:26\n    at file:///home/vicmca/CodeProjects/School/materiais/atividades/2c-revisao-01/node_modules/@vitest/runner/dist/index.js:1243:20\n    at new Promise (<anonymous>)\n    at runWithTimeout (file:///home/vicmca/CodeProjects/School/materiais/atividades/2c-revisao-01/node_modules/@vitest/runner/dist/index.js:1209:10)\n    at file:///home/vicmca/CodeProjects/School/materiais/atividades/2c-revisao-01/node_modules/@vitest/runner/dist/index.js:1653:37\n    at Traces.$ (file:///home/vicmca/CodeProjects/School/materiais/atividades/2c-revisao-01/node_modules/vitest/dist/chunks/traces.CCmnQaNT.js:142:27)\n    at trace (file:///home/vicmca/CodeProjects/School/materiais/atividades/2c-revisao-01/node_modules/vitest/dist/chunks/test.B8ej_ZHS.js:239:21)\n    at runTest (file:///home/vicmca/CodeProjects/School/materiais/atividades/2c-revisao-01/node_modules/@vitest/runner/dist/index.js:1653:12)"],"meta":{}},{"ancestorTitles":["Exercício 01"],"fullName":"Exercício 01 Ex01 - Correta - Questão 8","status":"failed","title":"Ex01 - Correta - Questão 8","duration":3.023055999999997,"failureMessages":["AssertionError: expected undefined to be type of 'boolean'\n    at /home/vicmca/CodeProjects/School/materiais/atividades/2c-revisao-01/ex01.test.js:28:30\n    at file:///home/vicmca/CodeProjects/School/materiais/atividades/2c-revisao-01/node_modules/@vitest/runner/dist/index.js:145:11\n    at file:///home/vicmca/CodeProjects/School/materiais/atividades/2c-revisao-01/node_modules/@vitest/runner/dist/index.js:915:26\n    at file:///home/vicmca/CodeProjects/School/materiais/atividades/2c-revisao-01/node_modules/@vitest/runner/dist/index.js:1243:20\n    at new Promise (<anonymous>)\n    at runWithTimeout (file:///home/vicmca/CodeProjects/School/materiais/atividades/2c-revisao-01/node_modules/@vitest/runner/dist/index.js:1209:10)\n    at file:///home/vicmca/CodeProjects/School/materiais/atividades/2c-revisao-01/node_modules/@vitest/runner/dist/index.js:1653:37\n    at Traces.$ (file:///home/vicmca/CodeProjects/School/materiais/atividades/2c-revisao-01/node_modules/vitest/dist/chunks/traces.CCmnQaNT.js:142:27)\n    at trace (file:///home/vicmca/CodeProjects/School/materiais/atividades/2c-revisao-01/node_modules/vitest/dist/chunks/test.B8ej_ZHS.js:239:21)\n    at runTest (file:///home/vicmca/CodeProjects/School/materiais/atividades/2c-revisao-01/node_modules/@vitest/runner/dist/index.js:1653:12)"],"meta":{}},{"ancestorTitles":["Exercício 01"],"fullName":"Exercício 01 Ex01 - Válida - Questão 9","status":"failed","title":"Ex01 - Válida - Questão 9","duration":2.432161000000008,"failureMessages":["AssertionError: expected undefined to be type of 'boolean'\n    at /home/vicmca/CodeProjects/School/materiais/atividades/2c-revisao-01/ex01.test.js:24:30\n    at file:///home/vicmca/CodeProjects/School/materiais/atividades/2c-revisao-01/node_modules/@vitest/runner/dist/index.js:145:11\n    at file:///home/vicmca/CodeProjects/School/materiais/atividades/2c-revisao-01/node_modules/@vitest/runner/dist/index.js:915:26\n    at file:///home/vicmca/CodeProjects/School/materiais/atividades/2c-revisao-01/node_modules/@vitest/runner/dist/index.js:1243:20\n    at new Promise (<anonymous>)\n    at runWithTimeout (file:///home/vicmca/CodeProjects/School/materiais/atividades/2c-revisao-01/node_modules/@vitest/runner/dist/index.js:1209:10)\n    at file:///home/vicmca/CodeProjects/School/materiais/atividades/2c-revisao-01/node_modules/@vitest/runner/dist/index.js:1653:37\n    at Traces.$ (file:///home/vicmca/CodeProjects/School/materiais/atividades/2c-revisao-01/node_modules/vitest/dist/chunks/traces.CCmnQaNT.js:142:27)\n    at trace (file:///home/vicmca/CodeProjects/School/materiais/atividades/2c-revisao-01/node_modules/vitest/dist/chunks/test.B8ej_ZHS.js:239:21)\n    at runTest (file:///home/vicmca/CodeProjects/School/materiais/atividades/2c-revisao-01/node_modules/@vitest/runner/dist/index.js:1653:12)"],"meta":{}},{"ancestorTitles":["Exercício 01"],"fullName":"Exercício 01 Ex01 - Correta - Questão 9","status":"failed","title":"Ex01 - Correta - Questão 9","duration":2.109831999999983,"failureMessages":["AssertionError: expected undefined to be type of 'boolean'\n    at /home/vicmca/CodeProjects/School/materiais/atividades/2c-revisao-01/ex01.test.js:28:30\n    at file:///home/vicmca/CodeProjects/School/materiais/atividades/2c-revisao-01/node_modules/@vitest/runner/dist/index.js:145:11\n    at file:///home/vicmca/CodeProjects/School/materiais/atividades/2c-revisao-01/node_modules/@vitest/runner/dist/index.js:915:26\n    at file:///home/vicmca/CodeProjects/School/materiais/atividades/2c-revisao-01/node_modules/@vitest/runner/dist/index.js:1243:20\n    at new Promise (<anonymous>)\n    at runWithTimeout (file:///home/vicmca/CodeProjects/School/materiais/atividades/2c-revisao-01/node_modules/@vitest/runner/dist/index.js:1209:10)\n    at file:///home/vicmca/CodeProjects/School/materiais/atividades/2c-revisao-01/node_modules/@vitest/runner/dist/index.js:1653:37\n    at Traces.$ (file:///home/vicmca/CodeProjects/School/materiais/atividades/2c-revisao-01/node_modules/vitest/dist/chunks/traces.CCmnQaNT.js:142:27)\n    at trace (file:///home/vicmca/CodeProjects/School/materiais/atividades/2c-revisao-01/node_modules/vitest/dist/chunks/test.B8ej_ZHS.js:239:21)\n    at runTest (file:///home/vicmca/CodeProjects/School/materiais/atividades/2c-revisao-01/node_modules/@vitest/runner/dist/index.js:1653:12)"],"meta":{}},{"ancestorTitles":["Exercício 01"],"fullName":"Exercício 01 Ex01 - Válida - Questão 10","status":"passed","title":"Ex01 - Válida - Questão 10","duration":0.4136259999999652,"failureMessages":[],"meta":{}},{"ancestorTitles":["Exercício 01"],"fullName":"Exercício 01 Ex01 - Correta - Questão 10","status":"passed","title":"Ex01 - Correta - Questão 10","duration":0.28385800000000927,"failureMessages":[],"meta":{}},{"ancestorTitles":["Exercício 01"],"fullName":"Exercício 01 Ex01 - Válida - Questão 11","status":"passed","title":"Ex01 - Válida - Questão 11","duration":0.33219300000001795,"failureMessages":[],"meta":{}},{"ancestorTitles":["Exercício 01"],"fullName":"Exercício 01 Ex01 - Correta - Questão 11","status":"passed","title":"Ex01 - Correta - Questão 11","duration":0.28357600000003913,"failureMessages":[],"meta":{}},{"ancestorTitles":["Exercício 01"],"fullName":"Exercício 01 Ex01 - Válida - Questão 12","status":"failed","title":"Ex01 - Válida - Questão 12","duration":4.083556000000044,"failureMessages":["AssertionError: expected undefined to be type of 'boolean'\n    at /home/vicmca/CodeProjects/School/materiais/atividades/2c-revisao-01/ex01.test.js:24:30\n    at file:///home/vicmca/CodeProjects/School/materiais/atividades/2c-revisao-01/node_modules/@vitest/runner/dist/index.js:145:11\n    at file:///home/vicmca/CodeProjects/School/materiais/atividades/2c-revisao-01/node_modules/@vitest/runner/dist/index.js:915:26\n    at file:///home/vicmca/CodeProjects/School/materiais/atividades/2c-revisao-01/node_modules/@vitest/runner/dist/index.js:1243:20\n    at new Promise (<anonymous>)\n    at runWithTimeout (file:///home/vicmca/CodeProjects/School/materiais/atividades/2c-revisao-01/node_modules/@vitest/runner/dist/index.js:1209:10)\n    at file:///home/vicmca/CodeProjects/School/materiais/atividades/2c-revisao-01/node_modules/@vitest/runner/dist/index.js:1653:37\n    at Traces.$ (file:///home/vicmca/CodeProjects/School/materiais/atividades/2c-revisao-01/node_modules/vitest/dist/chunks/traces.CCmnQaNT.js:142:27)\n    at trace (file:///home/vicmca/CodeProjects/School/materiais/atividades/2c-revisao-01/node_modules/vitest/dist/chunks/test.B8ej_ZHS.js:239:21)\n    at runTest (file:///home/vicmca/CodeProjects/School/materiais/atividades/2c-revisao-01/node_modules/@vitest/runner/dist/index.js:1653:12)"],"meta":{}},{"ancestorTitles":["Exercício 01"],"fullName":"Exercício 01 Ex01 - Correta - Questão 12","status":"failed","title":"Ex01 - Correta - Questão 12","duration":2.0865069999999832,"failureMessages":["AssertionError: expected undefined to be type of 'boolean'\n    at /home/vicmca/CodeProjects/School/materiais/atividades/2c-revisao-01/ex01.test.js:28:30\n    at file:///home/vicmca/CodeProjects/School/materiais/atividades/2c-revisao-01/node_modules/@vitest/runner/dist/index.js:145:11\n    at file:///home/vicmca/CodeProjects/School/materiais/atividades/2c-revisao-01/node_modules/@vitest/runner/dist/index.js:915:26\n    at file:///home/vicmca/CodeProjects/School/materiais/atividades/2c-revisao-01/node_modules/@vitest/runner/dist/index.js:1243:20\n    at new Promise (<anonymous>)\n    at runWithTimeout (file:///home/vicmca/CodeProjects/School/materiais/atividades/2c-revisao-01/node_modules/@vitest/runner/dist/index.js:1209:10)\n    at file:///home/vicmca/CodeProjects/School/materiais/atividades/2c-revisao-01/node_modules/@vitest/runner/dist/index.js:1653:37\n    at Traces.$ (file:///home/vicmca/CodeProjects/School/materiais/atividades/2c-revisao-01/node_modules/vitest/dist/chunks/traces.CCmnQaNT.js:142:27)\n    at trace (file:///home/vicmca/CodeProjects/School/materiais/atividades/2c-revisao-01/node_modules/vitest/dist/chunks/test.B8ej_ZHS.js:239:21)\n    at runTest (file:///home/vicmca/CodeProjects/School/materiais/atividades/2c-revisao-01/node_modules/@vitest/runner/dist/index.js:1653:12)"],"meta":{}},{"ancestorTitles":["Exercício 01"],"fullName":"Exercício 01 Ex01 - Válida - Questão 13","status":"failed","title":"Ex01 - Válida - Questão 13","duration":1.8165329999999358,"failureMessages":["AssertionError: expected undefined to be type of 'boolean'\n    at /home/vicmca/CodeProjects/School/materiais/atividades/2c-revisao-01/ex01.test.js:24:30\n    at file:///home/vicmca/CodeProjects/School/materiais/atividades/2c-revisao-01/node_modules/@vitest/runner/dist/index.js:145:11\n    at file:///home/vicmca/CodeProjects/School/materiais/atividades/2c-revisao-01/node_modules/@vitest/runner/dist/index.js:915:26\n    at file:///home/vicmca/CodeProjects/School/materiais/atividades/2c-revisao-01/node_modules/@vitest/runner/dist/index.js:1243:20\n    at new Promise (<anonymous>)\n    at runWithTimeout (file:///home/vicmca/CodeProjects/School/materiais/atividades/2c-revisao-01/node_modules/@vitest/runner/dist/index.js:1209:10)\n    at file:///home/vicmca/CodeProjects/School/materiais/atividades/2c-revisao-01/node_modules/@vitest/runner/dist/index.js:1653:37\n    at Traces.$ (file:///home/vicmca/CodeProjects/School/materiais/atividades/2c-revisao-01/node_modules/vitest/dist/chunks/traces.CCmnQaNT.js:142:27)\n    at trace (file:///home/vicmca/CodeProjects/School/materiais/atividades/2c-revisao-01/node_modules/vitest/dist/chunks/test.B8ej_ZHS.js:239:21)\n    at runTest (file:///home/vicmca/CodeProjects/School/materiais/atividades/2c-revisao-01/node_modules/@vitest/runner/dist/index.js:1653:12)"],"meta":{}},{"ancestorTitles":["Exercício 01"],"fullName":"Exercício 01 Ex01 - Correta - Questão 13","status":"failed","title":"Ex01 - Correta - Questão 13","duration":1.860873999999967,"failureMessages":["AssertionError: expected undefined to be type of 'boolean'\n    at /home/vicmca/CodeProjects/School/materiais/atividades/2c-revisao-01/ex01.test.js:28:30\n    at file:///home/vicmca/CodeProjects/School/materiais/atividades/2c-revisao-01/node_modules/@vitest/runner/dist/index.js:145:11\n    at file:///home/vicmca/CodeProjects/School/materiais/atividades/2c-revisao-01/node_modules/@vitest/runner/dist/index.js:915:26\n    at file:///home/vicmca/CodeProjects/School/materiais/atividades/2c-revisao-01/node_modules/@vitest/runner/dist/index.js:1243:20\n    at new Promise (<anonymous>)\n    at runWithTimeout (file:///home/vicmca/CodeProjects/School/materiais/atividades/2c-revisao-01/node_modules/@vitest/runner/dist/index.js:1209:10)\n    at file:///home/vicmca/CodeProjects/School/materiais/atividades/2c-revisao-01/node_modules/@vitest/runner/dist/index.js:1653:37\n    at Traces.$ (file:///home/vicmca/CodeProjects/School/materiais/atividades/2c-revisao-01/node_modules/vitest/dist/chunks/traces.CCmnQaNT.js:142:27)\n    at trace (file:///home/vicmca/CodeProjects/School/materiais/atividades/2c-revisao-01/node_modules/vitest/dist/chunks/test.B8ej_ZHS.js:239:21)\n    at runTest (file:///home/vicmca/CodeProjects/School/materiais/atividades/2c-revisao-01/node_modules/@vitest/runner/dist/index.js:1653:12)"],"meta":{}},{"ancestorTitles":["Exercício 01"],"fullName":"Exercício 01 Ex01 - Válida - Questão 14","status":"failed","title":"Ex01 - Válida - Questão 14","duration":8.211592999999993,"failureMessages":["AssertionError: expected undefined to be type of 'function'\n    at /home/vicmca/CodeProjects/School/materiais/atividades/2c-revisao-01/ex01.test.js:24:30\n    at file:///home/vicmca/CodeProjects/School/materiais/atividades/2c-revisao-01/node_modules/@vitest/runner/dist/index.js:145:11\n    at file:///home/vicmca/CodeProjects/School/materiais/atividades/2c-revisao-01/node_modules/@vitest/runner/dist/index.js:915:26\n    at file:///home/vicmca/CodeProjects/School/materiais/atividades/2c-revisao-01/node_modules/@vitest/runner/dist/index.js:1243:20\n    at new Promise (<anonymous>)\n    at runWithTimeout (file:///home/vicmca/CodeProjects/School/materiais/atividades/2c-revisao-01/node_modules/@vitest/runner/dist/index.js:1209:10)\n    at file:///home/vicmca/CodeProjects/School/materiais/atividades/2c-revisao-01/node_modules/@vitest/runner/dist/index.js:1653:37\n    at Traces.$ (file:///home/vicmca/CodeProjects/School/materiais/atividades/2c-revisao-01/node_modules/vitest/dist/chunks/traces.CCmnQaNT.js:142:27)\n    at trace (file:///home/vicmca/CodeProjects/School/materiais/atividades/2c-revisao-01/node_modules/vitest/dist/chunks/test.B8ej_ZHS.js:239:21)\n    at runTest (file:///home/vicmca/CodeProjects/School/materiais/atividades/2c-revisao-01/node_modules/@vitest/runner/dist/index.js:1653:12)"],"meta":{}},{"ancestorTitles":["Exercício 01"],"fullName":"Exercício 01 Ex01 - Correta - Questão 14","status":"failed","title":"Ex01 - Correta - Questão 14","duration":2.9912630000000036,"failureMessages":["AssertionError: expected undefined to be type of 'function'\n    at /home/vicmca/CodeProjects/School/materiais/atividades/2c-revisao-01/ex01.test.js:28:30\n    at file:///home/vicmca/CodeProjects/School/materiais/atividades/2c-revisao-01/node_modules/@vitest/runner/dist/index.js:145:11\n    at file:///home/vicmca/CodeProjects/School/materiais/atividades/2c-revisao-01/node_modules/@vitest/runner/dist/index.js:915:26\n    at file:///home/vicmca/CodeProjects/School/materiais/atividades/2c-revisao-01/node_modules/@vitest/runner/dist/index.js:1243:20\n    at new Promise (<anonymous>)\n    at runWithTimeout (file:///home/vicmca/CodeProjects/School/materiais/atividades/2c-revisao-01/node_modules/@vitest/runner/dist/index.js:1209:10)\n    at file:///home/vicmca/CodeProjects/School/materiais/atividades/2c-revisao-01/node_modules/@vitest/runner/dist/index.js:1653:37\n    at Traces.$ (file:///home/vicmca/CodeProjects/School/materiais/atividades/2c-revisao-01/node_modules/vitest/dist/chunks/traces.CCmnQaNT.js:142:27)\n    at trace (file:///home/vicmca/CodeProjects/School/materiais/atividades/2c-revisao-01/node_modules/vitest/dist/chunks/test.B8ej_ZHS.js:239:21)\n    at runTest (file:///home/vicmca/CodeProjects/School/materiais/atividades/2c-revisao-01/node_modules/@vitest/runner/dist/index.js:1653:12)"],"meta":{}},{"ancestorTitles":["Exercício 01"],"fullName":"Exercício 01 Ex01 - Válida - Questão 15","status":"failed","title":"Ex01 - Válida - Questão 15","duration":2.828700000000026,"failureMessages":["AssertionError: expected undefined to be type of 'function'\n    at /home/vicmca/CodeProjects/School/materiais/atividades/2c-revisao-01/ex01.test.js:24:30\n    at file:///home/vicmca/CodeProjects/School/materiais/atividades/2c-revisao-01/node_modules/@vitest/runner/dist/index.js:145:11\n    at file:///home/vicmca/CodeProjects/School/materiais/atividades/2c-revisao-01/node_modules/@vitest/runner/dist/index.js:915:26\n    at file:///home/vicmca/CodeProjects/School/materiais/atividades/2c-revisao-01/node_modules/@vitest/runner/dist/index.js:1243:20\n    at new Promise (<anonymous>)\n    at runWithTimeout (file:///home/vicmca/CodeProjects/School/materiais/atividades/2c-revisao-01/node_modules/@vitest/runner/dist/index.js:1209:10)\n    at file:///home/vicmca/CodeProjects/School/materiais/atividades/2c-revisao-01/node_modules/@vitest/runner/dist/index.js:1653:37\n    at Traces.$ (file:///home/vicmca/CodeProjects/School/materiais/atividades/2c-revisao-01/node_modules/vitest/dist/chunks/traces.CCmnQaNT.js:142:27)\n    at trace (file:///home/vicmca/CodeProjects/School/materiais/atividades/2c-revisao-01/node_modules/vitest/dist/chunks/test.B8ej_ZHS.js:239:21)\n    at runTest (file:///home/vicmca/CodeProjects/School/materiais/atividades/2c-revisao-01/node_modules/@vitest/runner/dist/index.js:1653:12)"],"meta":{}},{"ancestorTitles":["Exercício 01"],"fullName":"Exercício 01 Ex01 - Correta - Questão 15","status":"failed","title":"Ex01 - Correta - Questão 15","duration":2.815499999999929,"failureMessages":["AssertionError: expected undefined to be type of 'function'\n    at /home/vicmca/CodeProjects/School/materiais/atividades/2c-revisao-01/ex01.test.js:28:30\n    at file:///home/vicmca/CodeProjects/School/materiais/atividades/2c-revisao-01/node_modules/@vitest/runner/dist/index.js:145:11\n    at file:///home/vicmca/CodeProjects/School/materiais/atividades/2c-revisao-01/node_modules/@vitest/runner/dist/index.js:915:26\n    at file:///home/vicmca/CodeProjects/School/materiais/atividades/2c-revisao-01/node_modules/@vitest/runner/dist/index.js:1243:20\n    at new Promise (<anonymous>)\n    at runWithTimeout (file:///home/vicmca/CodeProjects/School/materiais/atividades/2c-revisao-01/node_modules/@vitest/runner/dist/index.js:1209:10)\n    at file:///home/vicmca/CodeProjects/School/materiais/atividades/2c-revisao-01/node_modules/@vitest/runner/dist/index.js:1653:37\n    at Traces.$ (file:///home/vicmca/CodeProjects/School/materiais/atividades/2c-revisao-01/node_modules/vitest/dist/chunks/traces.CCmnQaNT.js:142:27)\n    at trace (file:///home/vicmca/CodeProjects/School/materiais/atividades/2c-revisao-01/node_modules/vitest/dist/chunks/test.B8ej_ZHS.js:239:21)\n    at runTest (file:///home/vicmca/CodeProjects/School/materiais/atividades/2c-revisao-01/node_modules/@vitest/runner/dist/index.js:1653:12)"],"meta":{}},{"ancestorTitles":["Exercício 01"],"fullName":"Exercício 01 Ex01 - Válida - Questão 16","status":"failed","title":"Ex01 - Válida - Questão 16","duration":1.6527750000000196,"failureMessages":["AssertionError: expected undefined to be type of 'boolean'\n    at /home/vicmca/CodeProjects/School/materiais/atividades/2c-revisao-01/ex01.test.js:24:30\n    at file:///home/vicmca/CodeProjects/School/materiais/atividades/2c-revisao-01/node_modules/@vitest/runner/dist/index.js:145:11\n    at file:///home/vicmca/CodeProjects/School/materiais/atividades/2c-revisao-01/node_modules/@vitest/runner/dist/index.js:915:26\n    at file:///home/vicmca/CodeProjects/School/materiais/atividades/2c-revisao-01/node_modules/@vitest/runner/dist/index.js:1243:20\n    at new Promise (<anonymous>)\n    at runWithTimeout (file:///home/vicmca/CodeProjects/School/materiais/atividades/2c-revisao-01/node_modules/@vitest/runner/dist/index.js:1209:10)\n    at file:///home/vicmca/CodeProjects/School/materiais/atividades/2c-revisao-01/node_modules/@vitest/runner/dist/index.js:1653:37\n    at Traces.$ (file:///home/vicmca/CodeProjects/School/materiais/atividades/2c-revisao-01/node_modules/vitest/dist/chunks/traces.CCmnQaNT.js:142:27)\n    at trace (file:///home/vicmca/CodeProjects/School/materiais/atividades/2c-revisao-01/node_modules/vitest/dist/chunks/test.B8ej_ZHS.js:239:21)\n    at runTest (file:///home/vicmca/CodeProjects/School/materiais/atividades/2c-revisao-01/node_modules/@vitest/runner/dist/index.js:1653:12)"],"meta":{}},{"ancestorTitles":["Exercício 01"],"fullName":"Exercício 01 Ex01 - Correta - Questão 16","status":"failed","title":"Ex01 - Correta - Questão 16","duration":1.1030940000000555,"failureMessages":["AssertionError: expected undefined to be type of 'boolean'\n    at /home/vicmca/CodeProjects/School/materiais/atividades/2c-revisao-01/ex01.test.js:28:30\n    at file:///home/vicmca/CodeProjects/School/materiais/atividades/2c-revisao-01/node_modules/@vitest/runner/dist/index.js:145:11\n    at file:///home/vicmca/CodeProjects/School/materiais/atividades/2c-revisao-01/node_modules/@vitest/runner/dist/index.js:915:26\n    at file:///home/vicmca/CodeProjects/School/materiais/atividades/2c-revisao-01/node_modules/@vitest/runner/dist/index.js:1243:20\n    at new Promise (<anonymous>)\n    at runWithTimeout (file:///home/vicmca/CodeProjects/School/materiais/atividades/2c-revisao-01/node_modules/@vitest/runner/dist/index.js:1209:10)\n    at file:///home/vicmca/CodeProjects/School/materiais/atividades/2c-revisao-01/node_modules/@vitest/runner/dist/index.js:1653:37\n    at Traces.$ (file:///home/vicmca/CodeProjects/School/materiais/atividades/2c-revisao-01/node_modules/vitest/dist/chunks/traces.CCmnQaNT.js:142:27)\n    at trace (file:///home/vicmca/CodeProjects/School/materiais/atividades/2c-revisao-01/node_modules/vitest/dist/chunks/test.B8ej_ZHS.js:239:21)\n    at runTest (file:///home/vicmca/CodeProjects/School/materiais/atividades/2c-revisao-01/node_modules/@vitest/runner/dist/index.js:1653:12)"],"meta":{}},{"ancestorTitles":["Exercício 01"],"fullName":"Exercício 01 Ex01 - Válida - Questão 17","status":"failed","title":"Ex01 - Válida - Questão 17","duration":4.011810999999966,"failureMessages":["AssertionError: expected undefined to be type of 'boolean'\n    at /home/vicmca/CodeProjects/School/materiais/atividades/2c-revisao-01/ex01.test.js:24:30\n    at file:///home/vicmca/CodeProjects/School/materiais/atividades/2c-revisao-01/node_modules/@vitest/runner/dist/index.js:145:11\n    at file:///home/vicmca/CodeProjects/School/materiais/atividades/2c-revisao-01/node_modules/@vitest/runner/dist/index.js:915:26\n    at file:///home/vicmca/CodeProjects/School/materiais/atividades/2c-revisao-01/node_modules/@vitest/runner/dist/index.js:1243:20\n    at new Promise (<anonymous>)\n    at runWithTimeout (file:///home/vicmca/CodeProjects/School/materiais/atividades/2c-revisao-01/node_modules/@vitest/runner/dist/index.js:1209:10)\n    at file:///home/vicmca/CodeProjects/School/materiais/atividades/2c-revisao-01/node_modules/@vitest/runner/dist/index.js:1653:37\n    at Traces.$ (file:///home/vicmca/CodeProjects/School/materiais/atividades/2c-revisao-01/node_modules/vitest/dist/chunks/traces.CCmnQaNT.js:142:27)\n    at trace (file:///home/vicmca/CodeProjects/School/materiais/atividades/2c-revisao-01/node_modules/vitest/dist/chunks/test.B8ej_ZHS.js:239:21)\n    at runTest (file:///home/vicmca/CodeProjects/School/materiais/atividades/2c-revisao-01/node_modules/@vitest/runner/dist/index.js:1653:12)"],"meta":{}},{"ancestorTitles":["Exercício 01"],"fullName":"Exercício 01 Ex01 - Correta - Questão 17","status":"failed","title":"Ex01 - Correta - Questão 17","duration":6.144035000000031,"failureMessages":["AssertionError: expected undefined to be type of 'boolean'\n    at /home/vicmca/CodeProjects/School/materiais/atividades/2c-revisao-01/ex01.test.js:28:30\n    at file:///home/vicmca/CodeProjects/School/materiais/atividades/2c-revisao-01/node_modules/@vitest/runner/dist/index.js:145:11\n    at file:///home/vicmca/CodeProjects/School/materiais/atividades/2c-revisao-01/node_modules/@vitest/runner/dist/index.js:915:26\n    at file:///home/vicmca/CodeProjects/School/materiais/atividades/2c-revisao-01/node_modules/@vitest/runner/dist/index.js:1243:20\n    at new Promise (<anonymous>)\n    at runWithTimeout (file:///home/vicmca/CodeProjects/School/materiais/atividades/2c-revisao-01/node_modules/@vitest/runner/dist/index.js:1209:10)\n    at file:///home/vicmca/CodeProjects/School/materiais/atividades/2c-revisao-01/node_modules/@vitest/runner/dist/index.js:1653:37\n    at Traces.$ (file:///home/vicmca/CodeProjects/School/materiais/atividades/2c-revisao-01/node_modules/vitest/dist/chunks/traces.CCmnQaNT.js:142:27)\n    at trace (file:///home/vicmca/CodeProjects/School/materiais/atividades/2c-revisao-01/node_modules/vitest/dist/chunks/test.B8ej_ZHS.js:239:21)\n    at runTest (file:///home/vicmca/CodeProjects/School/materiais/atividades/2c-revisao-01/node_modules/@vitest/runner/dist/index.js:1653:12)"],"meta":{}},{"ancestorTitles":["Exercício 01"],"fullName":"Exercício 01 Ex01 - Válida - Questão 18","status":"failed","title":"Ex01 - Válida - Questão 18","duration":0.8068770000000995,"failureMessages":["AssertionError: expected undefined to be type of 'boolean'\n    at /home/vicmca/CodeProjects/School/materiais/atividades/2c-revisao-01/ex01.test.js:24:30\n    at file:///home/vicmca/CodeProjects/School/materiais/atividades/2c-revisao-01/node_modules/@vitest/runner/dist/index.js:145:11\n    at file:///home/vicmca/CodeProjects/School/materiais/atividades/2c-revisao-01/node_modules/@vitest/runner/dist/index.js:915:26\n    at file:///home/vicmca/CodeProjects/School/materiais/atividades/2c-revisao-01/node_modules/@vitest/runner/dist/index.js:1243:20\n    at new Promise (<anonymous>)\n    at runWithTimeout (file:///home/vicmca/CodeProjects/School/materiais/atividades/2c-revisao-01/node_modules/@vitest/runner/dist/index.js:1209:10)\n    at file:///home/vicmca/CodeProjects/School/materiais/atividades/2c-revisao-01/node_modules/@vitest/runner/dist/index.js:1653:37\n    at Traces.$ (file:///home/vicmca/CodeProjects/School/materiais/atividades/2c-revisao-01/node_modules/vitest/dist/chunks/traces.CCmnQaNT.js:142:27)\n    at trace (file:///home/vicmca/CodeProjects/School/materiais/atividades/2c-revisao-01/node_modules/vitest/dist/chunks/test.B8ej_ZHS.js:239:21)\n    at runTest (file:///home/vicmca/CodeProjects/School/materiais/atividades/2c-revisao-01/node_modules/@vitest/runner/dist/index.js:1653:12)"],"meta":{}},{"ancestorTitles":["Exercício 01"],"fullName":"Exercício 01 Ex01 - Correta - Questão 18","status":"failed","title":"Ex01 - Correta - Questão 18","duration":1.2637070000000676,"failureMessages":["AssertionError: expected undefined to be type of 'boolean'\n    at /home/vicmca/CodeProjects/School/materiais/atividades/2c-revisao-01/ex01.test.js:28:30\n    at file:///home/vicmca/CodeProjects/School/materiais/atividades/2c-revisao-01/node_modules/@vitest/runner/dist/index.js:145:11\n    at file:///home/vicmca/CodeProjects/School/materiais/atividades/2c-revisao-01/node_modules/@vitest/runner/dist/index.js:915:26\n    at file:///home/vicmca/CodeProjects/School/materiais/atividades/2c-revisao-01/node_modules/@vitest/runner/dist/index.js:1243:20\n    at new Promise (<anonymous>)\n    at runWithTimeout (file:///home/vicmca/CodeProjects/School/materiais/atividades/2c-revisao-01/node_modules/@vitest/runner/dist/index.js:1209:10)\n    at file:///home/vicmca/CodeProjects/School/materiais/atividades/2c-revisao-01/node_modules/@vitest/runner/dist/index.js:1653:37\n    at Traces.$ (file:///home/vicmca/CodeProjects/School/materiais/atividades/2c-revisao-01/node_modules/vitest/dist/chunks/traces.CCmnQaNT.js:142:27)\n    at trace (file:///home/vicmca/CodeProjects/School/materiais/atividades/2c-revisao-01/node_modules/vitest/dist/chunks/test.B8ej_ZHS.js:239:21)\n    at runTest (file:///home/vicmca/CodeProjects/School/materiais/atividades/2c-revisao-01/node_modules/@vitest/runner/dist/index.js:1653:12)"],"meta":{}},{"ancestorTitles":["Exercício 01"],"fullName":"Exercício 01 Ex01 - Válida - Questão 19","status":"failed","title":"Ex01 - Válida - Questão 19","duration":1.2131800000000794,"failureMessages":["AssertionError: expected undefined to be type of 'boolean'\n    at /home/vicmca/CodeProjects/School/materiais/atividades/2c-revisao-01/ex01.test.js:24:30\n    at file:///home/vicmca/CodeProjects/School/materiais/atividades/2c-revisao-01/node_modules/@vitest/runner/dist/index.js:145:11\n    at file:///home/vicmca/CodeProjects/School/materiais/atividades/2c-revisao-01/node_modules/@vitest/runner/dist/index.js:915:26\n    at file:///home/vicmca/CodeProjects/School/materiais/atividades/2c-revisao-01/node_modules/@vitest/runner/dist/index.js:1243:20\n    at new Promise (<anonymous>)\n    at runWithTimeout (file:///home/vicmca/CodeProjects/School/materiais/atividades/2c-revisao-01/node_modules/@vitest/runner/dist/index.js:1209:10)\n    at file:///home/vicmca/CodeProjects/School/materiais/atividades/2c-revisao-01/node_modules/@vitest/runner/dist/index.js:1653:37\n    at Traces.$ (file:///home/vicmca/CodeProjects/School/materiais/atividades/2c-revisao-01/node_modules/vitest/dist/chunks/traces.CCmnQaNT.js:142:27)\n    at trace (file:///home/vicmca/CodeProjects/School/materiais/atividades/2c-revisao-01/node_modules/vitest/dist/chunks/test.B8ej_ZHS.js:239:21)\n    at runTest (file:///home/vicmca/CodeProjects/School/materiais/atividades/2c-revisao-01/node_modules/@vitest/runner/dist/index.js:1653:12)"],"meta":{}},{"ancestorTitles":["Exercício 01"],"fullName":"Exercício 01 Ex01 - Correta - Questão 19","status":"failed","title":"Ex01 - Correta - Questão 19","duration":1.0957050000000663,"failureMessages":["AssertionError: expected undefined to be type of 'boolean'\n    at /home/vicmca/CodeProjects/School/materiais/atividades/2c-revisao-01/ex01.test.js:28:30\n    at file:///home/vicmca/CodeProjects/School/materiais/atividades/2c-revisao-01/node_modules/@vitest/runner/dist/index.js:145:11\n    at file:///home/vicmca/CodeProjects/School/materiais/atividades/2c-revisao-01/node_modules/@vitest/runner/dist/index.js:915:26\n    at file:///home/vicmca/CodeProjects/School/materiais/atividades/2c-revisao-01/node_modules/@vitest/runner/dist/index.js:1243:20\n    at new Promise (<anonymous>)\n    at runWithTimeout (file:///home/vicmca/CodeProjects/School/materiais/atividades/2c-revisao-01/node_modules/@vitest/runner/dist/index.js:1209:10)\n    at file:///home/vicmca/CodeProjects/School/materiais/atividades/2c-revisao-01/node_modules/@vitest/runner/dist/index.js:1653:37\n    at Traces.$ (file:///home/vicmca/CodeProjects/School/materiais/atividades/2c-revisao-01/node_modules/vitest/dist/chunks/traces.CCmnQaNT.js:142:27)\n    at trace (file:///home/vicmca/CodeProjects/School/materiais/atividades/2c-revisao-01/node_modules/vitest/dist/chunks/test.B8ej_ZHS.js:239:21)\n    at runTest (file:///home/vicmca/CodeProjects/School/materiais/atividades/2c-revisao-01/node_modules/@vitest/runner/dist/index.js:1653:12)"],"meta":{}},{"ancestorTitles":["Exercício 01"],"fullName":"Exercício 01 Ex01 - Válida - Questão 20","status":"failed","title":"Ex01 - Válida - Questão 20","duration":1.1574249999999893,"failureMessages":["AssertionError: expected undefined to be type of 'function'\n    at /home/vicmca/CodeProjects/School/materiais/atividades/2c-revisao-01/ex01.test.js:24:30\n    at file:///home/vicmca/CodeProjects/School/materiais/atividades/2c-revisao-01/node_modules/@vitest/runner/dist/index.js:145:11\n    at file:///home/vicmca/CodeProjects/School/materiais/atividades/2c-revisao-01/node_modules/@vitest/runner/dist/index.js:915:26\n    at file:///home/vicmca/CodeProjects/School/materiais/atividades/2c-revisao-01/node_modules/@vitest/runner/dist/index.js:1243:20\n    at new Promise (<anonymous>)\n    at runWithTimeout (file:///home/vicmca/CodeProjects/School/materiais/atividades/2c-revisao-01/node_modules/@vitest/runner/dist/index.js:1209:10)\n    at file:///home/vicmca/CodeProjects/School/materiais/atividades/2c-revisao-01/node_modules/@vitest/runner/dist/index.js:1653:37\n    at Traces.$ (file:///home/vicmca/CodeProjects/School/materiais/atividades/2c-revisao-01/node_modules/vitest/dist/chunks/traces.CCmnQaNT.js:142:27)\n    at trace (file:///home/vicmca/CodeProjects/School/materiais/atividades/2c-revisao-01/node_modules/vitest/dist/chunks/test.B8ej_ZHS.js:239:21)\n    at runTest (file:///home/vicmca/CodeProjects/School/materiais/atividades/2c-revisao-01/node_modules/@vitest/runner/dist/index.js:1653:12)"],"meta":{}},{"ancestorTitles":["Exercício 01"],"fullName":"Exercício 01 Ex01 - Correta - Questão 20","status":"failed","title":"Ex01 - Correta - Questão 20","duration":1.065148000000022,"failureMessages":["AssertionError: expected undefined to be type of 'function'\n    at /home/vicmca/CodeProjects/School/materiais/atividades/2c-revisao-01/ex01.test.js:28:30\n    at file:///home/vicmca/CodeProjects/School/materiais/atividades/2c-revisao-01/node_modules/@vitest/runner/dist/index.js:145:11\n    at file:///home/vicmca/CodeProjects/School/materiais/atividades/2c-revisao-01/node_modules/@vitest/runner/dist/index.js:915:26\n    at file:///home/vicmca/CodeProjects/School/materiais/atividades/2c-revisao-01/node_modules/@vitest/runner/dist/index.js:1243:20\n    at new Promise (<anonymous>)\n    at runWithTimeout (file:///home/vicmca/CodeProjects/School/materiais/atividades/2c-revisao-01/node_modules/@vitest/runner/dist/index.js:1209:10)\n    at file:///home/vicmca/CodeProjects/School/materiais/atividades/2c-revisao-01/node_modules/@vitest/runner/dist/index.js:1653:37\n    at Traces.$ (file:///home/vicmca/CodeProjects/School/materiais/atividades/2c-revisao-01/node_modules/vitest/dist/chunks/traces.CCmnQaNT.js:142:27)\n    at trace (file:///home/vicmca/CodeProjects/School/materiais/atividades/2c-revisao-01/node_modules/vitest/dist/chunks/test.B8ej_ZHS.js:239:21)\n    at runTest (file:///home/vicmca/CodeProjects/School/materiais/atividades/2c-revisao-01/node_modules/@vitest/runner/dist/index.js:1653:12)"],"meta":{}}],"startTime":1773084907122,"endTime":1773084907212.0652,"status":"failed","message":"","name":"/home/vicmca/CodeProjects/School/materiais/atividades/2c-revisao-01/ex01.test.js"},{"assertionResults":[{"ancestorTitles":["Exercício 02"],"fullName":"Exercício 02 Ex02 - Válida - Questão 1","status":"passed","title":"Ex02 - Válida - Questão 1","duration":3.6771270000000413,"failureMessages":[],"meta":{}},{"ancestorTitles":["Exercício 02"],"fullName":"Exercício 02 Ex02 - Correta - Questão 1","status":"passed","title":"Ex02 - Correta - Questão 1","duration":0.6312889999999811,"failureMessages":[],"meta":{}},{"ancestorTitles":["Exercício 02"],"fullName":"Exercício 02 Ex02 - Válida - Questão 2","status":"passed","title":"Ex02 - Válida - Questão 2","duration":0.44078799999999774,"failureMessages":[],"meta":{}},{"ancestorTitles":["Exercício 02"],"fullName":"Exercício 02 Ex02 - Correta - Questão 2","status":"passed","title":"Ex02 - Correta - Questão 2","duration":0.7923900000000117,"failureMessages":[],"meta":{}},{"ancestorTitles":["Exercício 02"],"fullName":"Exercício 02 Ex02 - Válida - Questão 3","status":"passed","title":"Ex02 - Válida - Questão 3","duration":0.5638869999999656,"failureMessages":[],"meta":{}},{"ancestorTitles":["Exercício 02"],"fullName":"Exercício 02 Ex02 - Correta - Questão 3","status":"passed","title":"Ex02 - Correta - Questão 3","duration":0.2881219999999871,"failureMessages":[],"meta":{}},{"ancestorTitles":["Exercício 02"],"fullName":"Exercício 02 Ex02 - Válida - Questão 4","status":"passed","title":"Ex02 - Válida - Questão 4","duration":0.6741570000000365,"failureMessages":[],"meta":{}},{"ancestorTitles":["Exercício 02"],"fullName":"Exercício 02 Ex02 - Correta - Questão 4","status":"passed","title":"Ex02 - Correta - Questão 4","duration":0.317908999999986,"failureMessages":[],"meta":{}},{"ancestorTitles":["Exercício 02"],"fullName":"Exercício 02 Ex02 - Válida - Questão 5","status":"passed","title":"Ex02 - Válida - Questão 5","duration":0.884001000000012,"failureMessages":[],"meta":{}},{"ancestorTitles":["Exercício 02"],"fullName":"Exercício 02 Ex02 - Correta - Questão 5","status":"passed","title":"Ex02 - Correta - Questão 5","duration":0.3996920000000159,"failureMessages":[],"meta":{}},{"ancestorTitles":["Exercício 02"],"fullName":"Exercício 02 Ex02 - Válida - Questão 6","status":"passed","title":"Ex02 - Válida - Questão 6","duration":0.3139099999999644,"failureMessages":[],"meta":{}},{"ancestorTitles":["Exercício 02"],"fullName":"Exercício 02 Ex02 - Correta - Questão 6","status":"passed","title":"Ex02 - Correta - Questão 6","duration":0.17838599999998905,"failureMessages":[],"meta":{}},{"ancestorTitles":["Exercício 02"],"fullName":"Exercício 02 Ex02 - Válida - Questão 7","status":"passed","title":"Ex02 - Válida - Questão 7","duration":0.27762200000000803,"failureMessages":[],"meta":{}},{"ancestorTitles":["Exercício 02"],"fullName":"Exercício 02 Ex02 - Correta - Questão 7","status":"passed","title":"Ex02 - Correta - Questão 7","duration":0.20921800000002122,"failureMessages":[],"meta":{}},{"ancestorTitles":["Exercício 02"],"fullName":"Exercício 02 Ex02 - Válida - Questão 8","status":"passed","title":"Ex02 - Válida - Questão 8","duration":0.29665799999997944,"failureMessages":[],"meta":{}},{"ancestorTitles":["Exercício 02"],"fullName":"Exercício 02 Ex02 - Correta - Questão 8","status":"passed","title":"Ex02 - Correta - Questão 8","duration":0.19539300000002413,"failureMessages":[],"meta":{}},{"ancestorTitles":["Exercício 02"],"fullName":"Exercício 02 Ex02 - Válida - Questão 9","status":"passed","title":"Ex02 - Válida - Questão 9","duration":0.8227380000000153,"failureMessages":[],"meta":{}},{"ancestorTitles":["Exercício 02"],"fullName":"Exercício 02 Ex02 - Correta - Questão 9","status":"passed","title":"Ex02 - Correta - Questão 9","duration":0.23937899999998535,"failureMessages":[],"meta":{}},{"ancestorTitles":["Exercício 02"],"fullName":"Exercício 02 Ex02 - Válida - Questão 10","status":"passed","title":"Ex02 - Válida - Questão 10","duration":0.3273889999999824,"failureMessages":[],"meta":{}},{"ancestorTitles":["Exercício 02"],"fullName":"Exercício 02 Ex02 - Correta - Questão 10","status":"passed","title":"Ex02 - Correta - Questão 10","duration":0.22162899999995034,"failureMessages":[],"meta":{}},{"ancestorTitles":["Exercício 02"],"fullName":"Exercício 02 Ex02 - Válida - Questão 11","status":"failed","title":"Ex02 - Válida - Questão 11","duration":22.492032999999992,"failureMessages":["AssertionError: expected undefined to be type of 'boolean'\n    at /home/vicmca/CodeProjects/School/materiais/atividades/2c-revisao-01/ex02.test.js:25:30\n    at file:///home/vicmca/CodeProjects/School/materiais/atividades/2c-revisao-01/node_modules/@vitest/runner/dist/index.js:145:11\n    at file:///home/vicmca/CodeProjects/School/materiais/atividades/2c-revisao-01/node_modules/@vitest/runner/dist/index.js:915:26\n    at file:///home/vicmca/CodeProjects/School/materiais/atividades/2c-revisao-01/node_modules/@vitest/runner/dist/index.js:1243:20\n    at new Promise (<anonymous>)\n    at runWithTimeout (file:///home/vicmca/CodeProjects/School/materiais/atividades/2c-revisao-01/node_modules/@vitest/runner/dist/index.js:1209:10)\n    at file:///home/vicmca/CodeProjects/School/materiais/atividades/2c-revisao-01/node_modules/@vitest/runner/dist/index.js:1653:37\n    at Traces.$ (file:///home/vicmca/CodeProjects/School/materiais/atividades/2c-revisao-01/node_modules/vitest/dist/chunks/traces.CCmnQaNT.js:142:27)\n    at trace (file:///home/vicmca/CodeProjects/School/materiais/atividades/2c-revisao-01/node_modules/vitest/dist/chunks/test.B8ej_ZHS.js:239:21)\n    at runTest (file:///home/vicmca/CodeProjects/School/materiais/atividades/2c-revisao-01/node_modules/@vitest/runner/dist/index.js:1653:12)"],"meta":{}},{"ancestorTitles":["Exercício 02"],"fullName":"Exercício 02 Ex02 - Correta - Questão 11","status":"passed","title":"Ex02 - Correta - Questão 11","duration":0.31770499999998947,"failureMessages":[],"meta":{}},{"ancestorTitles":["Exercício 02"],"fullName":"Exercício 02 Ex02 - Válida - Questão 12","status":"failed","title":"Ex02 - Válida - Questão 12","duration":3.3986090000000218,"failureMessages":["AssertionError: expected undefined to be type of 'number'\n    at /home/vicmca/CodeProjects/School/materiais/atividades/2c-revisao-01/ex02.test.js:25:30\n    at file:///home/vicmca/CodeProjects/School/materiais/atividades/2c-revisao-01/node_modules/@vitest/runner/dist/index.js:145:11\n    at file:///home/vicmca/CodeProjects/School/materiais/atividades/2c-revisao-01/node_modules/@vitest/runner/dist/index.js:915:26\n    at file:///home/vicmca/CodeProjects/School/materiais/atividades/2c-revisao-01/node_modules/@vitest/runner/dist/index.js:1243:20\n    at new Promise (<anonymous>)\n    at runWithTimeout (file:///home/vicmca/CodeProjects/School/materiais/atividades/2c-revisao-01/node_modules/@vitest/runner/dist/index.js:1209:10)\n    at file:///home/vicmca/CodeProjects/School/materiais/atividades/2c-revisao-01/node_modules/@vitest/runner/dist/index.js:1653:37\n    at Traces.$ (file:///home/vicmca/CodeProjects/School/materiais/atividades/2c-revisao-01/node_modules/vitest/dist/chunks/traces.CCmnQaNT.js:142:27)\n    at trace (file:///home/vicmca/CodeProjects/School/materiais/atividades/2c-revisao-01/node_modules/vitest/dist/chunks/test.B8ej_ZHS.js:239:21)\n    at runTest (file:///home/vicmca/CodeProjects/School/materiais/atividades/2c-revisao-01/node_modules/@vitest/runner/dist/index.js:1653:12)"],"meta":{}},{"ancestorTitles":["Exercício 02"],"fullName":"Exercício 02 Ex02 - Correta - Questão 12","status":"passed","title":"Ex02 - Correta - Questão 12","duration":0.30751400000002604,"failureMessages":[],"meta":{}},{"ancestorTitles":["Exercício 02"],"fullName":"Exercício 02 Ex02 - Válida - Questão 13","status":"failed","title":"Ex02 - Válida - Questão 13","duration":2.1402499999999804,"failureMessages":["AssertionError: expected undefined to be type of 'string'\n    at /home/vicmca/CodeProjects/School/materiais/atividades/2c-revisao-01/ex02.test.js:25:30\n    at file:///home/vicmca/CodeProjects/School/materiais/atividades/2c-revisao-01/node_modules/@vitest/runner/dist/index.js:145:11\n    at file:///home/vicmca/CodeProjects/School/materiais/atividades/2c-revisao-01/node_modules/@vitest/runner/dist/index.js:915:26\n    at file:///home/vicmca/CodeProjects/School/materiais/atividades/2c-revisao-01/node_modules/@vitest/runner/dist/index.js:1243:20\n    at new Promise (<anonymous>)\n    at runWithTimeout (file:///home/vicmca/CodeProjects/School/materiais/atividades/2c-revisao-01/node_modules/@vitest/runner/dist/index.js:1209:10)\n    at file:///home/vicmca/CodeProjects/School/materiais/atividades/2c-revisao-01/node_modules/@vitest/runner/dist/index.js:1653:37\n    at Traces.$ (file:///home/vicmca/CodeProjects/School/materiais/atividades/2c-revisao-01/node_modules/vitest/dist/chunks/traces.CCmnQaNT.js:142:27)\n    at trace (file:///home/vicmca/CodeProjects/School/materiais/atividades/2c-revisao-01/node_modules/vitest/dist/chunks/test.B8ej_ZHS.js:239:21)\n    at runTest (file:///home/vicmca/CodeProjects/School/materiais/atividades/2c-revisao-01/node_modules/@vitest/runner/dist/index.js:1653:12)"],"meta":{}},{"ancestorTitles":["Exercício 02"],"fullName":"Exercício 02 Ex02 - Correta - Questão 13","status":"passed","title":"Ex02 - Correta - Questão 13","duration":0.27343700000000126,"failureMessages":[],"meta":{}},{"ancestorTitles":["Exercício 02"],"fullName":"Exercício 02 Ex02 - Válida - Questão 14","status":"failed","title":"Ex02 - Válida - Questão 14","duration":2.0035589999999956,"failureMessages":["AssertionError: expected undefined to be type of 'string'\n    at /home/vicmca/CodeProjects/School/materiais/atividades/2c-revisao-01/ex02.test.js:25:30\n    at file:///home/vicmca/CodeProjects/School/materiais/atividades/2c-revisao-01/node_modules/@vitest/runner/dist/index.js:145:11\n    at file:///home/vicmca/CodeProjects/School/materiais/atividades/2c-revisao-01/node_modules/@vitest/runner/dist/index.js:915:26\n    at file:///home/vicmca/CodeProjects/School/materiais/atividades/2c-revisao-01/node_modules/@vitest/runner/dist/index.js:1243:20\n    at new Promise (<anonymous>)\n    at runWithTimeout (file:///home/vicmca/CodeProjects/School/materiais/atividades/2c-revisao-01/node_modules/@vitest/runner/dist/index.js:1209:10)\n    at file:///home/vicmca/CodeProjects/School/materiais/atividades/2c-revisao-01/node_modules/@vitest/runner/dist/index.js:1653:37\n    at Traces.$ (file:///home/vicmca/CodeProjects/School/materiais/atividades/2c-revisao-01/node_modules/vitest/dist/chunks/traces.CCmnQaNT.js:142:27)\n    at trace (file:///home/vicmca/CodeProjects/School/materiais/atividades/2c-revisao-01/node_modules/vitest/dist/chunks/test.B8ej_ZHS.js:239:21)\n    at runTest (file:///home/vicmca/CodeProjects/School/materiais/atividades/2c-revisao-01/node_modules/@vitest/runner/dist/index.js:1653:12)"],"meta":{}},{"ancestorTitles":["Exercício 02"],"fullName":"Exercício 02 Ex02 - Correta - Questão 14","status":"passed","title":"Ex02 - Correta - Questão 14","duration":0.27612599999997656,"failureMessages":[],"meta":{}},{"ancestorTitles":["Exercício 02"],"fullName":"Exercício 02 Ex02 - Válida - Questão 15","status":"failed","title":"Ex02 - Válida - Questão 15","duration":3.06260199999997,"failureMessages":["AssertionError: expected undefined to be type of 'number'\n    at /home/vicmca/CodeProjects/School/materiais/atividades/2c-revisao-01/ex02.test.js:25:30\n    at file:///home/vicmca/CodeProjects/School/materiais/atividades/2c-revisao-01/node_modules/@vitest/runner/dist/index.js:145:11\n    at file:///home/vicmca/CodeProjects/School/materiais/atividades/2c-revisao-01/node_modules/@vitest/runner/dist/index.js:915:26\n    at file:///home/vicmca/CodeProjects/School/materiais/atividades/2c-revisao-01/node_modules/@vitest/runner/dist/index.js:1243:20\n    at new Promise (<anonymous>)\n    at runWithTimeout (file:///home/vicmca/CodeProjects/School/materiais/atividades/2c-revisao-01/node_modules/@vitest/runner/dist/index.js:1209:10)\n    at file:///home/vicmca/CodeProjects/School/materiais/atividades/2c-revisao-01/node_modules/@vitest/runner/dist/index.js:1653:37\n    at Traces.$ (file:///home/vicmca/CodeProjects/School/materiais/atividades/2c-revisao-01/node_modules/vitest/dist/chunks/traces.CCmnQaNT.js:142:27)\n    at trace (file:///home/vicmca/CodeProjects/School/materiais/atividades/2c-revisao-01/node_modules/vitest/dist/chunks/test.B8ej_ZHS.js:239:21)\n    at runTest (file:///home/vicmca/CodeProjects/School/materiais/atividades/2c-revisao-01/node_modules/@vitest/runner/dist/index.js:1653:12)"],"meta":{}},{"ancestorTitles":["Exercício 02"],"fullName":"Exercício 02 Ex02 - Correta - Questão 15","status":"passed","title":"Ex02 - Correta - Questão 15","duration":0.2750289999999609,"failureMessages":[],"meta":{}},{"ancestorTitles":["Exercício 02"],"fullName":"Exercício 02 Ex02 - Válida - Questão 16","status":"failed","title":"Ex02 - Válida - Questão 16","duration":1.9563049999999862,"failureMessages":["AssertionError: expected undefined to be type of 'boolean'\n    at /home/vicmca/CodeProjects/School/materiais/atividades/2c-revisao-01/ex02.test.js:25:30\n    at file:///home/vicmca/CodeProjects/School/materiais/atividades/2c-revisao-01/node_modules/@vitest/runner/dist/index.js:145:11\n    at file:///home/vicmca/CodeProjects/School/materiais/atividades/2c-revisao-01/node_modules/@vitest/runner/dist/index.js:915:26\n    at file:///home/vicmca/CodeProjects/School/materiais/atividades/2c-revisao-01/node_modules/@vitest/runner/dist/index.js:1243:20\n    at new Promise (<anonymous>)\n    at runWithTimeout (file:///home/vicmca/CodeProjects/School/materiais/atividades/2c-revisao-01/node_modules/@vitest/runner/dist/index.js:1209:10)\n    at file:///home/vicmca/CodeProjects/School/materiais/atividades/2c-revisao-01/node_modules/@vitest/runner/dist/index.js:1653:37\n    at Traces.$ (file:///home/vicmca/CodeProjects/School/materiais/atividades/2c-revisao-01/node_modules/vitest/dist/chunks/traces.CCmnQaNT.js:142:27)\n    at trace (file:///home/vicmca/CodeProjects/School/materiais/atividades/2c-revisao-01/node_modules/vitest/dist/chunks/test.B8ej_ZHS.js:239:21)\n    at runTest (file:///home/vicmca/CodeProjects/School/materiais/atividades/2c-revisao-01/node_modules/@vitest/runner/dist/index.js:1653:12)"],"meta":{}},{"ancestorTitles":["Exercício 02"],"fullName":"Exercício 02 Ex02 - Correta - Questão 16","status":"passed","title":"Ex02 - Correta - Questão 16","duration":0.20461400000004915,"failureMessages":[],"meta":{}},{"ancestorTitles":["Exercício 02"],"fullName":"Exercício 02 Ex02 - Válida - Questão 17","status":"failed","title":"Ex02 - Válida - Questão 17","duration":1.2499559999999974,"failureMessages":["AssertionError: expected undefined to be type of 'string'\n    at /home/vicmca/CodeProjects/School/materiais/atividades/2c-revisao-01/ex02.test.js:25:30\n    at file:///home/vicmca/CodeProjects/School/materiais/atividades/2c-revisao-01/node_modules/@vitest/runner/dist/index.js:145:11\n    at file:///home/vicmca/CodeProjects/School/materiais/atividades/2c-revisao-01/node_modules/@vitest/runner/dist/index.js:915:26\n    at file:///home/vicmca/CodeProjects/School/materiais/atividades/2c-revisao-01/node_modules/@vitest/runner/dist/index.js:1243:20\n    at new Promise (<anonymous>)\n    at runWithTimeout (file:///home/vicmca/CodeProjects/School/materiais/atividades/2c-revisao-01/node_modules/@vitest/runner/dist/index.js:1209:10)\n    at file:///home/vicmca/CodeProjects/School/materiais/atividades/2c-revisao-01/node_modules/@vitest/runner/dist/index.js:1653:37\n    at Traces.$ (file:///home/vicmca/CodeProjects/School/materiais/atividades/2c-revisao-01/node_modules/vitest/dist/chunks/traces.CCmnQaNT.js:142:27)\n    at trace (file:///home/vicmca/CodeProjects/School/materiais/atividades/2c-revisao-01/node_modules/vitest/dist/chunks/test.B8ej_ZHS.js:239:21)\n    at runTest (file:///home/vicmca/CodeProjects/School/materiais/atividades/2c-revisao-01/node_modules/@vitest/runner/dist/index.js:1653:12)"],"meta":{}},{"ancestorTitles":["Exercício 02"],"fullName":"Exercício 02 Ex02 - Correta - Questão 17","status":"passed","title":"Ex02 - Correta - Questão 17","duration":0.193224999999984,"failureMessages":[],"meta":{}},{"ancestorTitles":["Exercício 02"],"fullName":"Exercício 02 Ex02 - Válida - Questão 18","status":"failed","title":"Ex02 - Válida - Questão 18","duration":1.1840230000000247,"failureMessages":["AssertionError: expected undefined to be type of 'boolean'\n    at /home/vicmca/CodeProjects/School/materiais/atividades/2c-revisao-01/ex02.test.js:25:30\n    at file:///home/vicmca/CodeProjects/School/materiais/atividades/2c-revisao-01/node_modules/@vitest/runner/dist/index.js:145:11\n    at file:///home/vicmca/CodeProjects/School/materiais/atividades/2c-revisao-01/node_modules/@vitest/runner/dist/index.js:915:26\n    at file:///home/vicmca/CodeProjects/School/materiais/atividades/2c-revisao-01/node_modules/@vitest/runner/dist/index.js:1243:20\n    at new Promise (<anonymous>)\n    at runWithTimeout (file:///home/vicmca/CodeProjects/School/materiais/atividades/2c-revisao-01/node_modules/@vitest/runner/dist/index.js:1209:10)\n    at file:///home/vicmca/CodeProjects/School/materiais/atividades/2c-revisao-01/node_modules/@vitest/runner/dist/index.js:1653:37\n    at Traces.$ (file:///home/vicmca/CodeProjects/School/materiais/atividades/2c-revisao-01/node_modules/vitest/dist/chunks/traces.CCmnQaNT.js:142:27)\n    at trace (file:///home/vicmca/CodeProjects/School/materiais/atividades/2c-revisao-01/node_modules/vitest/dist/chunks/test.B8ej_ZHS.js:239:21)\n    at runTest (file:///home/vicmca/CodeProjects/School/materiais/atividades/2c-revisao-01/node_modules/@vitest/runner/dist/index.js:1653:12)"],"meta":{}},{"ancestorTitles":["Exercício 02"],"fullName":"Exercício 02 Ex02 - Correta - Questão 18","status":"passed","title":"Ex02 - Correta - Questão 18","duration":0.1783299999999599,"failureMessages":[],"meta":{}},{"ancestorTitles":["Exercício 02"],"fullName":"Exercício 02 Ex02 - Válida - Questão 19","status":"failed","title":"Ex02 - Válida - Questão 19","duration":1.7558549999999968,"failureMessages":["AssertionError: expected undefined to be type of 'object'\n    at /home/vicmca/CodeProjects/School/materiais/atividades/2c-revisao-01/ex02.test.js:25:30\n    at file:///home/vicmca/CodeProjects/School/materiais/atividades/2c-revisao-01/node_modules/@vitest/runner/dist/index.js:145:11\n    at file:///home/vicmca/CodeProjects/School/materiais/atividades/2c-revisao-01/node_modules/@vitest/runner/dist/index.js:915:26\n    at file:///home/vicmca/CodeProjects/School/materiais/atividades/2c-revisao-01/node_modules/@vitest/runner/dist/index.js:1243:20\n    at new Promise (<anonymous>)\n    at runWithTimeout (file:///home/vicmca/CodeProjects/School/materiais/atividades/2c-revisao-01/node_modules/@vitest/runner/dist/index.js:1209:10)\n    at file:///home/vicmca/CodeProjects/School/materiais/atividades/2c-revisao-01/node_modules/@vitest/runner/dist/index.js:1653:37\n    at Traces.$ (file:///home/vicmca/CodeProjects/School/materiais/atividades/2c-revisao-01/node_modules/vitest/dist/chunks/traces.CCmnQaNT.js:142:27)\n    at trace (file:///home/vicmca/CodeProjects/School/materiais/atividades/2c-revisao-01/node_modules/vitest/dist/chunks/test.B8ej_ZHS.js:239:21)\n    at runTest (file:///home/vicmca/CodeProjects/School/materiais/atividades/2c-revisao-01/node_modules/@vitest/runner/dist/index.js:1653:12)"],"meta":{}},{"ancestorTitles":["Exercício 02"],"fullName":"Exercício 02 Ex02 - Correta - Questão 19","status":"passed","title":"Ex02 - Correta - Questão 19","duration":0.19439899999997579,"failureMessages":[],"meta":{}},{"ancestorTitles":["Exercício 02"],"fullName":"Exercício 02 Ex02 - Válida - Questão 20","status":"failed","title":"Ex02 - Válida - Questão 20","duration":1.4611939999999777,"failureMessages":["AssertionError: expected undefined to be type of 'boolean'\n    at /home/vicmca/CodeProjects/School/materiais/atividades/2c-revisao-01/ex02.test.js:25:30\n    at file:///home/vicmca/CodeProjects/School/materiais/atividades/2c-revisao-01/node_modules/@vitest/runner/dist/index.js:145:11\n    at file:///home/vicmca/CodeProjects/School/materiais/atividades/2c-revisao-01/node_modules/@vitest/runner/dist/index.js:915:26\n    at file:///home/vicmca/CodeProjects/School/materiais/atividades/2c-revisao-01/node_modules/@vitest/runner/dist/index.js:1243:20\n    at new Promise (<anonymous>)\n    at runWithTimeout (file:///home/vicmca/CodeProjects/School/materiais/atividades/2c-revisao-01/node_modules/@vitest/runner/dist/index.js:1209:10)\n    at file:///home/vicmca/CodeProjects/School/materiais/atividades/2c-revisao-01/node_modules/@vitest/runner/dist/index.js:1653:37\n    at Traces.$ (file:///home/vicmca/CodeProjects/School/materiais/atividades/2c-revisao-01/node_modules/vitest/dist/chunks/traces.CCmnQaNT.js:142:27)\n    at trace (file:///home/vicmca/CodeProjects/School/materiais/atividades/2c-revisao-01/node_modules/vitest/dist/chunks/test.B8ej_ZHS.js:239:21)\n    at runTest (file:///home/vicmca/CodeProjects/School/materiais/atividades/2c-revisao-01/node_modules/@vitest/runner/dist/index.js:1653:12)"],"meta":{}},{"ancestorTitles":["Exercício 02"],"fullName":"Exercício 02 Ex02 - Correta - Questão 20","status":"passed","title":"Ex02 - Correta - Questão 20","duration":0.18429600000001756,"failureMessages":[],"meta":{}}],"startTime":1773084907105,"endTime":1773084907162.1843,"status":"failed","message":"","name":"/home/vicmca/CodeProjects/School/materiais/atividades/2c-revisao-01/ex02.test.js"},{"assertionResults":[{"ancestorTitles":["Exercício 03"],"fullName":"Exercício 03 ex03 - Válida - Questão 1","status":"passed","title":"ex03 - Válida - Questão 1","duration":3.114212000000009,"failureMessages":[],"meta":{}},{"ancestorTitles":["Exercício 03"],"fullName":"Exercício 03 ex03 - Correta - Questão 1","status":"passed","title":"ex03 - Correta - Questão 1","duration":0.7828570000000354,"failureMessages":[],"meta":{}},{"ancestorTitles":["Exercício 03"],"fullName":"Exercício 03 ex03 - Válida - Questão 2","status":"passed","title":"ex03 - Válida - Questão 2","duration":0.5384119999999939,"failureMessages":[],"meta":{}},{"ancestorTitles":["Exercício 03"],"fullName":"Exercício 03 ex03 - Correta - Questão 2","status":"passed","title":"ex03 - Correta - Questão 2","duration":0.9350989999999797,"failureMessages":[],"meta":{}},{"ancestorTitles":["Exercício 03"],"fullName":"Exercício 03 ex03 - Válida - Questão 3","status":"passed","title":"ex03 - Válida - Questão 3","duration":0.6263309999999933,"failureMessages":[],"meta":{}},{"ancestorTitles":["Exercício 03"],"fullName":"Exercício 03 ex03 - Correta - Questão 3","status":"passed","title":"ex03 - Correta - Questão 3","duration":0.35727900000000545,"failureMessages":[],"meta":{}},{"ancestorTitles":["Exercício 03"],"fullName":"Exercício 03 ex03 - Válida - Questão 4","status":"passed","title":"ex03 - Válida - Questão 4","duration":0.8049260000000231,"failureMessages":[],"meta":{}},{"ancestorTitles":["Exercício 03"],"fullName":"Exercício 03 ex03 - Correta - Questão 4","status":"passed","title":"ex03 - Correta - Questão 4","duration":0.3750970000000393,"failureMessages":[],"meta":{}},{"ancestorTitles":["Exercício 03"],"fullName":"Exercício 03 ex03 - Válida - Questão 5","status":"passed","title":"ex03 - Válida - Questão 5","duration":0.9499459999999544,"failureMessages":[],"meta":{}},{"ancestorTitles":["Exercício 03"],"fullName":"Exercício 03 ex03 - Correta - Questão 5","status":"passed","title":"ex03 - Correta - Questão 5","duration":0.30683299999998326,"failureMessages":[],"meta":{}},{"ancestorTitles":["Exercício 03"],"fullName":"Exercício 03 ex03 - Válida - Questão 6","status":"failed","title":"ex03 - Válida - Questão 6","duration":15.829864999999984,"failureMessages":["AssertionError: expected undefined to be type of 'boolean'\n    at /home/vicmca/CodeProjects/School/materiais/atividades/2c-revisao-01/ex03.test.js:19:30\n    at file:///home/vicmca/CodeProjects/School/materiais/atividades/2c-revisao-01/node_modules/@vitest/runner/dist/index.js:145:11\n    at file:///home/vicmca/CodeProjects/School/materiais/atividades/2c-revisao-01/node_modules/@vitest/runner/dist/index.js:915:26\n    at file:///home/vicmca/CodeProjects/School/materiais/atividades/2c-revisao-01/node_modules/@vitest/runner/dist/index.js:1243:20\n    at new Promise (<anonymous>)\n    at runWithTimeout (file:///home/vicmca/CodeProjects/School/materiais/atividades/2c-revisao-01/node_modules/@vitest/runner/dist/index.js:1209:10)\n    at file:///home/vicmca/CodeProjects/School/materiais/atividades/2c-revisao-01/node_modules/@vitest/runner/dist/index.js:1653:37\n    at Traces.$ (file:///home/vicmca/CodeProjects/School/materiais/atividades/2c-revisao-01/node_modules/vitest/dist/chunks/traces.CCmnQaNT.js:142:27)\n    at trace (file:///home/vicmca/CodeProjects/School/materiais/atividades/2c-revisao-01/node_modules/vitest/dist/chunks/test.B8ej_ZHS.js:239:21)\n    at runTest (file:///home/vicmca/CodeProjects/School/materiais/atividades/2c-revisao-01/node_modules/@vitest/runner/dist/index.js:1653:12)"],"meta":{}},{"ancestorTitles":["Exercício 03"],"fullName":"Exercício 03 ex03 - Correta - Questão 6","status":"passed","title":"ex03 - Correta - Questão 6","duration":0.291971999999987,"failureMessages":[],"meta":{}},{"ancestorTitles":["Exercício 03"],"fullName":"Exercício 03 ex03 - Válida - Questão 7","status":"failed","title":"ex03 - Válida - Questão 7","duration":2.5412739999999303,"failureMessages":["AssertionError: expected undefined to be type of 'boolean'\n    at /home/vicmca/CodeProjects/School/materiais/atividades/2c-revisao-01/ex03.test.js:19:30\n    at file:///home/vicmca/CodeProjects/School/materiais/atividades/2c-revisao-01/node_modules/@vitest/runner/dist/index.js:145:11\n    at file:///home/vicmca/CodeProjects/School/materiais/atividades/2c-revisao-01/node_modules/@vitest/runner/dist/index.js:915:26\n    at file:///home/vicmca/CodeProjects/School/materiais/atividades/2c-revisao-01/node_modules/@vitest/runner/dist/index.js:1243:20\n    at new Promise (<anonymous>)\n    at runWithTimeout (file:///home/vicmca/CodeProjects/School/materiais/atividades/2c-revisao-01/node_modules/@vitest/runner/dist/index.js:1209:10)\n    at file:///home/vicmca/CodeProjects/School/materiais/atividades/2c-revisao-01/node_modules/@vitest/runner/dist/index.js:1653:37\n    at Traces.$ (file:///home/vicmca/CodeProjects/School/materiais/atividades/2c-revisao-01/node_modules/vitest/dist/chunks/traces.CCmnQaNT.js:142:27)\n    at trace (file:///home/vicmca/CodeProjects/School/materiais/atividades/2c-revisao-01/node_modules/vitest/dist/chunks/test.B8ej_ZHS.js:239:21)\n    at runTest (file:///home/vicmca/CodeProjects/School/materiais/atividades/2c-revisao-01/node_modules/@vitest/runner/dist/index.js:1653:12)"],"meta":{}},{"ancestorTitles":["Exercício 03"],"fullName":"Exercício 03 ex03 - Correta - Questão 7","status":"passed","title":"ex03 - Correta - Questão 7","duration":0.2534500000000435,"failureMessages":[],"meta":{}},{"ancestorTitles":["Exercício 03"],"fullName":"Exercício 03 ex03 - Válida - Questão 8","status":"failed","title":"ex03 - Válida - Questão 8","duration":2.1050689999999577,"failureMessages":["AssertionError: expected undefined to be type of 'boolean'\n    at /home/vicmca/CodeProjects/School/materiais/atividades/2c-revisao-01/ex03.test.js:19:30\n    at file:///home/vicmca/CodeProjects/School/materiais/atividades/2c-revisao-01/node_modules/@vitest/runner/dist/index.js:145:11\n    at file:///home/vicmca/CodeProjects/School/materiais/atividades/2c-revisao-01/node_modules/@vitest/runner/dist/index.js:915:26\n    at file:///home/vicmca/CodeProjects/School/materiais/atividades/2c-revisao-01/node_modules/@vitest/runner/dist/index.js:1243:20\n    at new Promise (<anonymous>)\n    at runWithTimeout (file:///home/vicmca/CodeProjects/School/materiais/atividades/2c-revisao-01/node_modules/@vitest/runner/dist/index.js:1209:10)\n    at file:///home/vicmca/CodeProjects/School/materiais/atividades/2c-revisao-01/node_modules/@vitest/runner/dist/index.js:1653:37\n    at Traces.$ (file:///home/vicmca/CodeProjects/School/materiais/atividades/2c-revisao-01/node_modules/vitest/dist/chunks/traces.CCmnQaNT.js:142:27)\n    at trace (file:///home/vicmca/CodeProjects/School/materiais/atividades/2c-revisao-01/node_modules/vitest/dist/chunks/test.B8ej_ZHS.js:239:21)\n    at runTest (file:///home/vicmca/CodeProjects/School/materiais/atividades/2c-revisao-01/node_modules/@vitest/runner/dist/index.js:1653:12)"],"meta":{}},{"ancestorTitles":["Exercício 03"],"fullName":"Exercício 03 ex03 - Correta - Questão 8","status":"passed","title":"ex03 - Correta - Questão 8","duration":0.3103770000000168,"failureMessages":[],"meta":{}},{"ancestorTitles":["Exercício 03"],"fullName":"Exercício 03 ex03 - Válida - Questão 9","status":"failed","title":"ex03 - Válida - Questão 9","duration":1.570363000000043,"failureMessages":["AssertionError: expected undefined to be type of 'boolean'\n    at /home/vicmca/CodeProjects/School/materiais/atividades/2c-revisao-01/ex03.test.js:19:30\n    at file:///home/vicmca/CodeProjects/School/materiais/atividades/2c-revisao-01/node_modules/@vitest/runner/dist/index.js:145:11\n    at file:///home/vicmca/CodeProjects/School/materiais/atividades/2c-revisao-01/node_modules/@vitest/runner/dist/index.js:915:26\n    at file:///home/vicmca/CodeProjects/School/materiais/atividades/2c-revisao-01/node_modules/@vitest/runner/dist/index.js:1243:20\n    at new Promise (<anonymous>)\n    at runWithTimeout (file:///home/vicmca/CodeProjects/School/materiais/atividades/2c-revisao-01/node_modules/@vitest/runner/dist/index.js:1209:10)\n    at file:///home/vicmca/CodeProjects/School/materiais/atividades/2c-revisao-01/node_modules/@vitest/runner/dist/index.js:1653:37\n    at Traces.$ (file:///home/vicmca/CodeProjects/School/materiais/atividades/2c-revisao-01/node_modules/vitest/dist/chunks/traces.CCmnQaNT.js:142:27)\n    at trace (file:///home/vicmca/CodeProjects/School/materiais/atividades/2c-revisao-01/node_modules/vitest/dist/chunks/test.B8ej_ZHS.js:239:21)\n    at runTest (file:///home/vicmca/CodeProjects/School/materiais/atividades/2c-revisao-01/node_modules/@vitest/runner/dist/index.js:1653:12)"],"meta":{}},{"ancestorTitles":["Exercício 03"],"fullName":"Exercício 03 ex03 - Correta - Questão 9","status":"passed","title":"ex03 - Correta - Questão 9","duration":0.1775480000000016,"failureMessages":[],"meta":{}},{"ancestorTitles":["Exercício 03"],"fullName":"Exercício 03 ex03 - Válida - Questão 10","status":"failed","title":"ex03 - Válida - Questão 10","duration":2.174268999999981,"failureMessages":["AssertionError: expected undefined to be type of 'boolean'\n    at /home/vicmca/CodeProjects/School/materiais/atividades/2c-revisao-01/ex03.test.js:19:30\n    at file:///home/vicmca/CodeProjects/School/materiais/atividades/2c-revisao-01/node_modules/@vitest/runner/dist/index.js:145:11\n    at file:///home/vicmca/CodeProjects/School/materiais/atividades/2c-revisao-01/node_modules/@vitest/runner/dist/index.js:915:26\n    at file:///home/vicmca/CodeProjects/School/materiais/atividades/2c-revisao-01/node_modules/@vitest/runner/dist/index.js:1243:20\n    at new Promise (<anonymous>)\n    at runWithTimeout (file:///home/vicmca/CodeProjects/School/materiais/atividades/2c-revisao-01/node_modules/@vitest/runner/dist/index.js:1209:10)\n    at file:///home/vicmca/CodeProjects/School/materiais/atividades/2c-revisao-01/node_modules/@vitest/runner/dist/index.js:1653:37\n    at Traces.$ (file:///home/vicmca/CodeProjects/School/materiais/atividades/2c-revisao-01/node_modules/vitest/dist/chunks/traces.CCmnQaNT.js:142:27)\n    at trace (file:///home/vicmca/CodeProjects/School/materiais/atividades/2c-revisao-01/node_modules/vitest/dist/chunks/test.B8ej_ZHS.js:239:21)\n    at runTest (file:///home/vicmca/CodeProjects/School/materiais/atividades/2c-revisao-01/node_modules/@vitest/runner/dist/index.js:1653:12)"],"meta":{}},{"ancestorTitles":["Exercício 03"],"fullName":"Exercício 03 ex03 - Correta - Questão 10","status":"passed","title":"ex03 - Correta - Questão 10","duration":0.21892800000000534,"failureMessages":[],"meta":{}}],"startTime":1773084907704,"endTime":1773084907740.219,"status":"failed","message":"","name":"/home/vicmca/CodeProjects/School/materiais/atividades/2c-revisao-01/ex03.test.js"},{"assertionResults":[{"ancestorTitles":["Exercício 04"],"fullName":"Exercício 04 ex04 - Válida - Questão 1","status":"passed","title":"ex04 - Válida - Questão 1","duration":3.8412680000000137,"failureMessages":[],"meta":{}},{"ancestorTitles":["Exercício 04"],"fullName":"Exercício 04 ex04 - Correta - Questão 1","status":"passed","title":"ex04 - Correta - Questão 1","duration":0.7468200000000138,"failureMessages":[],"meta":{}},{"ancestorTitles":["Exercício 04"],"fullName":"Exercício 04 ex04 - Válida - Questão 2","status":"passed","title":"ex04 - Válida - Questão 2","duration":0.4762890000000084,"failureMessages":[],"meta":{}},{"ancestorTitles":["Exercício 04"],"fullName":"Exercício 04 ex04 - Correta - Questão 2","status":"passed","title":"ex04 - Correta - Questão 2","duration":0.8634120000000394,"failureMessages":[],"meta":{}},{"ancestorTitles":["Exercício 04"],"fullName":"Exercício 04 ex04 - Válida - Questão 3","status":"passed","title":"ex04 - Válida - Questão 3","duration":0.4450379999999541,"failureMessages":[],"meta":{}},{"ancestorTitles":["Exercício 04"],"fullName":"Exercício 04 ex04 - Correta - Questão 3","status":"passed","title":"ex04 - Correta - Questão 3","duration":0.2291569999999865,"failureMessages":[],"meta":{}},{"ancestorTitles":["Exercício 04"],"fullName":"Exercício 04 ex04 - Válida - Questão 4","status":"passed","title":"ex04 - Válida - Questão 4","duration":0.7732710000000225,"failureMessages":[],"meta":{}},{"ancestorTitles":["Exercício 04"],"fullName":"Exercício 04 ex04 - Correta - Questão 4","status":"passed","title":"ex04 - Correta - Questão 4","duration":0.39938000000000784,"failureMessages":[],"meta":{}},{"ancestorTitles":["Exercício 04"],"fullName":"Exercício 04 ex04 - Válida - Questão 5","status":"passed","title":"ex04 - Válida - Questão 5","duration":0.9310249999999769,"failureMessages":[],"meta":{}},{"ancestorTitles":["Exercício 04"],"fullName":"Exercício 04 ex04 - Correta - Questão 5","status":"passed","title":"ex04 - Correta - Questão 5","duration":0.3635110000000168,"failureMessages":[],"meta":{}},{"ancestorTitles":["Exercício 04"],"fullName":"Exercício 04 ex04 - Válida - Questão 6","status":"passed","title":"ex04 - Válida - Questão 6","duration":0.2447819999999865,"failureMessages":[],"meta":{}},{"ancestorTitles":["Exercício 04"],"fullName":"Exercício 04 ex04 - Correta - Questão 6","status":"passed","title":"ex04 - Correta - Questão 6","duration":0.1368190000000027,"failureMessages":[],"meta":{}},{"ancestorTitles":["Exercício 04"],"fullName":"Exercício 04 ex04 - Válida - Questão 7","status":"passed","title":"ex04 - Válida - Questão 7","duration":0.19503599999995913,"failureMessages":[],"meta":{}},{"ancestorTitles":["Exercício 04"],"fullName":"Exercício 04 ex04 - Correta - Questão 7","status":"passed","title":"ex04 - Correta - Questão 7","duration":0.1389560000000074,"failureMessages":[],"meta":{}},{"ancestorTitles":["Exercício 04"],"fullName":"Exercício 04 ex04 - Válida - Questão 8","status":"passed","title":"ex04 - Válida - Questão 8","duration":0.20063899999996693,"failureMessages":[],"meta":{}},{"ancestorTitles":["Exercício 04"],"fullName":"Exercício 04 ex04 - Correta - Questão 8","status":"passed","title":"ex04 - Correta - Questão 8","duration":0.12717600000001994,"failureMessages":[],"meta":{}},{"ancestorTitles":["Exercício 04"],"fullName":"Exercício 04 ex04 - Válida - Questão 9","status":"passed","title":"ex04 - Válida - Questão 9","duration":0.2889059999999972,"failureMessages":[],"meta":{}},{"ancestorTitles":["Exercício 04"],"fullName":"Exercício 04 ex04 - Correta - Questão 9","status":"passed","title":"ex04 - Correta - Questão 9","duration":0.13201200000003155,"failureMessages":[],"meta":{}},{"ancestorTitles":["Exercício 04"],"fullName":"Exercício 04 ex04 - Válida - Questão 10","status":"passed","title":"ex04 - Válida - Questão 10","duration":0.25789300000002413,"failureMessages":[],"meta":{}},{"ancestorTitles":["Exercício 04"],"fullName":"Exercício 04 ex04 - Correta - Questão 10","status":"passed","title":"ex04 - Correta - Questão 10","duration":0.14569499999998925,"failureMessages":[],"meta":{}},{"ancestorTitles":["Exercício 04"],"fullName":"Exercício 04 ex04 - Válida - Questão 11","status":"passed","title":"ex04 - Válida - Questão 11","duration":0.18589600000001383,"failureMessages":[],"meta":{}},{"ancestorTitles":["Exercício 04"],"fullName":"Exercício 04 ex04 - Correta - Questão 11","status":"passed","title":"ex04 - Correta - Questão 11","duration":0.19771599999995715,"failureMessages":[],"meta":{}},{"ancestorTitles":["Exercício 04"],"fullName":"Exercício 04 ex04 - Válida - Questão 12","status":"passed","title":"ex04 - Válida - Questão 12","duration":0.29748499999999467,"failureMessages":[],"meta":{}},{"ancestorTitles":["Exercício 04"],"fullName":"Exercício 04 ex04 - Correta - Questão 12","status":"passed","title":"ex04 - Correta - Questão 12","duration":0.15691500000002634,"failureMessages":[],"meta":{}},{"ancestorTitles":["Exercício 04"],"fullName":"Exercício 04 ex04 - Válida - Questão 13","status":"passed","title":"ex04 - Válida - Questão 13","duration":0.19863699999996243,"failureMessages":[],"meta":{}},{"ancestorTitles":["Exercício 04"],"fullName":"Exercício 04 ex04 - Correta - Questão 13","status":"passed","title":"ex04 - Correta - Questão 13","duration":0.12119500000000016,"failureMessages":[],"meta":{}},{"ancestorTitles":["Exercício 04"],"fullName":"Exercício 04 ex04 - Válida - Questão 14","status":"passed","title":"ex04 - Válida - Questão 14","duration":0.18674800000002278,"failureMessages":[],"meta":{}},{"ancestorTitles":["Exercício 04"],"fullName":"Exercício 04 ex04 - Correta - Questão 14","status":"passed","title":"ex04 - Correta - Questão 14","duration":0.10990099999997938,"failureMessages":[],"meta":{}},{"ancestorTitles":["Exercício 04"],"fullName":"Exercício 04 ex04 - Válida - Questão 15","status":"passed","title":"ex04 - Válida - Questão 15","duration":0.16204700000002958,"failureMessages":[],"meta":{}},{"ancestorTitles":["Exercício 04"],"fullName":"Exercício 04 ex04 - Correta - Questão 15","status":"passed","title":"ex04 - Correta - Questão 15","duration":0.11051900000001069,"failureMessages":[],"meta":{}},{"ancestorTitles":["Exercício 04"],"fullName":"Exercício 04 ex04 - Válida - Questão 16","status":"passed","title":"ex04 - Válida - Questão 16","duration":0.2767949999999928,"failureMessages":[],"meta":{}},{"ancestorTitles":["Exercício 04"],"fullName":"Exercício 04 ex04 - Correta - Questão 16","status":"passed","title":"ex04 - Correta - Questão 16","duration":0.1564100000000508,"failureMessages":[],"meta":{}},{"ancestorTitles":["Exercício 04"],"fullName":"Exercício 04 ex04 - Válida - Questão 17","status":"passed","title":"ex04 - Válida - Questão 17","duration":0.1727210000000241,"failureMessages":[],"meta":{}},{"ancestorTitles":["Exercício 04"],"fullName":"Exercício 04 ex04 - Correta - Questão 17","status":"passed","title":"ex04 - Correta - Questão 17","duration":0.11539200000004257,"failureMessages":[],"meta":{}},{"ancestorTitles":["Exercício 04"],"fullName":"Exercício 04 ex04 - Válida - Questão 18","status":"passed","title":"ex04 - Válida - Questão 18","duration":0.1713100000000054,"failureMessages":[],"meta":{}},{"ancestorTitles":["Exercício 04"],"fullName":"Exercício 04 ex04 - Correta - Questão 18","status":"passed","title":"ex04 - Correta - Questão 18","duration":0.11401299999999992,"failureMessages":[],"meta":{}},{"ancestorTitles":["Exercício 04"],"fullName":"Exercício 04 ex04 - Válida - Questão 19","status":"passed","title":"ex04 - Válida - Questão 19","duration":0.17110700000000634,"failureMessages":[],"meta":{}},{"ancestorTitles":["Exercício 04"],"fullName":"Exercício 04 ex04 - Correta - Questão 19","status":"passed","title":"ex04 - Correta - Questão 19","duration":0.11429000000003953,"failureMessages":[],"meta":{}},{"ancestorTitles":["Exercício 04"],"fullName":"Exercício 04 ex04 - Válida - Questão 20","status":"passed","title":"ex04 - Válida - Questão 20","duration":0.1681899999999814,"failureMessages":[],"meta":{}},{"ancestorTitles":["Exercício 04"],"fullName":"Exercício 04 ex04 - Correta - Questão 20","status":"passed","title":"ex04 - Correta - Questão 20","duration":0.18959999999998445,"failureMessages":[],"meta":{}}],"startTime":1773084907663,"endTime":1773084907679.1897,"status":"passed","message":"","name":"/home/vicmca/CodeProjects/School/materiais/atividades/2c-revisao-01/ex04.test.js"},{"assertionResults":[{"ancestorTitles":["Exercício 05"],"fullName":"Exercício 05 ex05 - Válida - Questão 1","status":"passed","title":"ex05 - Válida - Questão 1","duration":4.11096699999996,"failureMessages":[],"meta":{}},{"ancestorTitles":["Exercício 05"],"fullName":"Exercício 05 ex05 - Correta - Questão 1","status":"passed","title":"ex05 - Correta - Questão 1","duration":1.0743190000000027,"failureMessages":[],"meta":{}},{"ancestorTitles":["Exercício 05"],"fullName":"Exercício 05 ex05 - Válida - Questão 2","status":"passed","title":"ex05 - Válida - Questão 2","duration":0.561035000000004,"failureMessages":[],"meta":{}},{"ancestorTitles":["Exercício 05"],"fullName":"Exercício 05 ex05 - Correta - Questão 2","status":"passed","title":"ex05 - Correta - Questão 2","duration":0.969963000000007,"failureMessages":[],"meta":{}},{"ancestorTitles":["Exercício 05"],"fullName":"Exercício 05 ex05 - Válida - Questão 3","status":"passed","title":"ex05 - Válida - Questão 3","duration":0.55243999999999,"failureMessages":[],"meta":{}},{"ancestorTitles":["Exercício 05"],"fullName":"Exercício 05 ex05 - Correta - Questão 3","status":"passed","title":"ex05 - Correta - Questão 3","duration":0.360149999999976,"failureMessages":[],"meta":{}},{"ancestorTitles":["Exercício 05"],"fullName":"Exercício 05 ex05 - Válida - Questão 4","status":"passed","title":"ex05 - Válida - Questão 4","duration":0.6778590000000122,"failureMessages":[],"meta":{}},{"ancestorTitles":["Exercício 05"],"fullName":"Exercício 05 ex05 - Correta - Questão 4","status":"passed","title":"ex05 - Correta - Questão 4","duration":0.584513999999956,"failureMessages":[],"meta":{}},{"ancestorTitles":["Exercício 05"],"fullName":"Exercício 05 ex05 - Válida - Questão 5","status":"passed","title":"ex05 - Válida - Questão 5","duration":1.1798630000000117,"failureMessages":[],"meta":{}},{"ancestorTitles":["Exercício 05"],"fullName":"Exercício 05 ex05 - Correta - Questão 5","status":"passed","title":"ex05 - Correta - Questão 5","duration":0.5028519999999617,"failureMessages":[],"meta":{}},{"ancestorTitles":["Exercício 05"],"fullName":"Exercício 05 ex05 - Válida - Questão 6","status":"passed","title":"ex05 - Válida - Questão 6","duration":0.3946189999999774,"failureMessages":[],"meta":{}},{"ancestorTitles":["Exercício 05"],"fullName":"Exercício 05 ex05 - Correta - Questão 6","status":"passed","title":"ex05 - Correta - Questão 6","duration":0.2976309999999671,"failureMessages":[],"meta":{}},{"ancestorTitles":["Exercício 05"],"fullName":"Exercício 05 ex05 - Válida - Questão 7","status":"passed","title":"ex05 - Válida - Questão 7","duration":0.3204970000000458,"failureMessages":[],"meta":{}},{"ancestorTitles":["Exercício 05"],"fullName":"Exercício 05 ex05 - Correta - Questão 7","status":"failed","title":"ex05 - Correta - Questão 7","duration":23.017586999999992,"failureMessages":["AssertionError: expected false to be true // Object.is equality\n    at /home/vicmca/CodeProjects/School/materiais/atividades/2c-revisao-01/ex05.test.js:17:29\n    at file:///home/vicmca/CodeProjects/School/materiais/atividades/2c-revisao-01/node_modules/@vitest/runner/dist/index.js:145:11\n    at file:///home/vicmca/CodeProjects/School/materiais/atividades/2c-revisao-01/node_modules/@vitest/runner/dist/index.js:915:26\n    at file:///home/vicmca/CodeProjects/School/materiais/atividades/2c-revisao-01/node_modules/@vitest/runner/dist/index.js:1243:20\n    at new Promise (<anonymous>)\n    at runWithTimeout (file:///home/vicmca/CodeProjects/School/materiais/atividades/2c-revisao-01/node_modules/@vitest/runner/dist/index.js:1209:10)\n    at file:///home/vicmca/CodeProjects/School/materiais/atividades/2c-revisao-01/node_modules/@vitest/runner/dist/index.js:1653:37\n    at Traces.$ (file:///home/vicmca/CodeProjects/School/materiais/atividades/2c-revisao-01/node_modules/vitest/dist/chunks/traces.CCmnQaNT.js:142:27)\n    at trace (file:///home/vicmca/CodeProjects/School/materiais/atividades/2c-revisao-01/node_modules/vitest/dist/chunks/test.B8ej_ZHS.js:239:21)\n    at runTest (file:///home/vicmca/CodeProjects/School/materiais/atividades/2c-revisao-01/node_modules/@vitest/runner/dist/index.js:1653:12)"],"meta":{}},{"ancestorTitles":["Exercício 05"],"fullName":"Exercício 05 ex05 - Válida - Questão 8","status":"failed","title":"ex05 - Válida - Questão 8","duration":7.437696000000017,"failureMessages":["AssertionError: expected 20 to be type of 'boolean'\n    at /home/vicmca/CodeProjects/School/materiais/atividades/2c-revisao-01/ex05.test.js:14:30\n    at file:///home/vicmca/CodeProjects/School/materiais/atividades/2c-revisao-01/node_modules/@vitest/runner/dist/index.js:145:11\n    at file:///home/vicmca/CodeProjects/School/materiais/atividades/2c-revisao-01/node_modules/@vitest/runner/dist/index.js:915:26\n    at file:///home/vicmca/CodeProjects/School/materiais/atividades/2c-revisao-01/node_modules/@vitest/runner/dist/index.js:1243:20\n    at new Promise (<anonymous>)\n    at runWithTimeout (file:///home/vicmca/CodeProjects/School/materiais/atividades/2c-revisao-01/node_modules/@vitest/runner/dist/index.js:1209:10)\n    at file:///home/vicmca/CodeProjects/School/materiais/atividades/2c-revisao-01/node_modules/@vitest/runner/dist/index.js:1653:37\n    at Traces.$ (file:///home/vicmca/CodeProjects/School/materiais/atividades/2c-revisao-01/node_modules/vitest/dist/chunks/traces.CCmnQaNT.js:142:27)\n    at trace (file:///home/vicmca/CodeProjects/School/materiais/atividades/2c-revisao-01/node_modules/vitest/dist/chunks/test.B8ej_ZHS.js:239:21)\n    at runTest (file:///home/vicmca/CodeProjects/School/materiais/atividades/2c-revisao-01/node_modules/@vitest/runner/dist/index.js:1653:12)"],"meta":{}},{"ancestorTitles":["Exercício 05"],"fullName":"Exercício 05 ex05 - Correta - Questão 8","status":"failed","title":"ex05 - Correta - Questão 8","duration":2.4366870000000063,"failureMessages":["AssertionError: expected 20 to be true // Object.is equality\n    at /home/vicmca/CodeProjects/School/materiais/atividades/2c-revisao-01/ex05.test.js:17:29\n    at file:///home/vicmca/CodeProjects/School/materiais/atividades/2c-revisao-01/node_modules/@vitest/runner/dist/index.js:145:11\n    at file:///home/vicmca/CodeProjects/School/materiais/atividades/2c-revisao-01/node_modules/@vitest/runner/dist/index.js:915:26\n    at file:///home/vicmca/CodeProjects/School/materiais/atividades/2c-revisao-01/node_modules/@vitest/runner/dist/index.js:1243:20\n    at new Promise (<anonymous>)\n    at runWithTimeout (file:///home/vicmca/CodeProjects/School/materiais/atividades/2c-revisao-01/node_modules/@vitest/runner/dist/index.js:1209:10)\n    at file:///home/vicmca/CodeProjects/School/materiais/atividades/2c-revisao-01/node_modules/@vitest/runner/dist/index.js:1653:37\n    at Traces.$ (file:///home/vicmca/CodeProjects/School/materiais/atividades/2c-revisao-01/node_modules/vitest/dist/chunks/traces.CCmnQaNT.js:142:27)\n    at trace (file:///home/vicmca/CodeProjects/School/materiais/atividades/2c-revisao-01/node_modules/vitest/dist/chunks/test.B8ej_ZHS.js:239:21)\n    at runTest (file:///home/vicmca/CodeProjects/School/materiais/atividades/2c-revisao-01/node_modules/@vitest/runner/dist/index.js:1653:12)"],"meta":{}},{"ancestorTitles":["Exercício 05"],"fullName":"Exercício 05 ex05 - Válida - Questão 9","status":"failed","title":"ex05 - Válida - Questão 9","duration":2.770431999999971,"failureMessages":["AssertionError: expected 'fido' to be type of 'boolean'\n    at /home/vicmca/CodeProjects/School/materiais/atividades/2c-revisao-01/ex05.test.js:14:30\n    at file:///home/vicmca/CodeProjects/School/materiais/atividades/2c-revisao-01/node_modules/@vitest/runner/dist/index.js:145:11\n    at file:///home/vicmca/CodeProjects/School/materiais/atividades/2c-revisao-01/node_modules/@vitest/runner/dist/index.js:915:26\n    at file:///home/vicmca/CodeProjects/School/materiais/atividades/2c-revisao-01/node_modules/@vitest/runner/dist/index.js:1243:20\n    at new Promise (<anonymous>)\n    at runWithTimeout (file:///home/vicmca/CodeProjects/School/materiais/atividades/2c-revisao-01/node_modules/@vitest/runner/dist/index.js:1209:10)\n    at file:///home/vicmca/CodeProjects/School/materiais/atividades/2c-revisao-01/node_modules/@vitest/runner/dist/index.js:1653:37\n    at Traces.$ (file:///home/vicmca/CodeProjects/School/materiais/atividades/2c-revisao-01/node_modules/vitest/dist/chunks/traces.CCmnQaNT.js:142:27)\n    at trace (file:///home/vicmca/CodeProjects/School/materiais/atividades/2c-revisao-01/node_modules/vitest/dist/chunks/test.B8ej_ZHS.js:239:21)\n    at runTest (file:///home/vicmca/CodeProjects/School/materiais/atividades/2c-revisao-01/node_modules/@vitest/runner/dist/index.js:1653:12)"],"meta":{}},{"ancestorTitles":["Exercício 05"],"fullName":"Exercício 05 ex05 - Correta - Questão 9","status":"failed","title":"ex05 - Correta - Questão 9","duration":2.6116139999999746,"failureMessages":["AssertionError: expected 'fido' to be true // Object.is equality\n    at /home/vicmca/CodeProjects/School/materiais/atividades/2c-revisao-01/ex05.test.js:17:29\n    at file:///home/vicmca/CodeProjects/School/materiais/atividades/2c-revisao-01/node_modules/@vitest/runner/dist/index.js:145:11\n    at file:///home/vicmca/CodeProjects/School/materiais/atividades/2c-revisao-01/node_modules/@vitest/runner/dist/index.js:915:26\n    at file:///home/vicmca/CodeProjects/School/materiais/atividades/2c-revisao-01/node_modules/@vitest/runner/dist/index.js:1243:20\n    at new Promise (<anonymous>)\n    at runWithTimeout (file:///home/vicmca/CodeProjects/School/materiais/atividades/2c-revisao-01/node_modules/@vitest/runner/dist/index.js:1209:10)\n    at file:///home/vicmca/CodeProjects/School/materiais/atividades/2c-revisao-01/node_modules/@vitest/runner/dist/index.js:1653:37\n    at Traces.$ (file:///home/vicmca/CodeProjects/School/materiais/atividades/2c-revisao-01/node_modules/vitest/dist/chunks/traces.CCmnQaNT.js:142:27)\n    at trace (file:///home/vicmca/CodeProjects/School/materiais/atividades/2c-revisao-01/node_modules/vitest/dist/chunks/test.B8ej_ZHS.js:239:21)\n    at runTest (file:///home/vicmca/CodeProjects/School/materiais/atividades/2c-revisao-01/node_modules/@vitest/runner/dist/index.js:1653:12)"],"meta":{}},{"ancestorTitles":["Exercício 05"],"fullName":"Exercício 05 ex05 - Válida - Questão 10","status":"passed","title":"ex05 - Válida - Questão 10","duration":0.4726510000000417,"failureMessages":[],"meta":{}},{"ancestorTitles":["Exercício 05"],"fullName":"Exercício 05 ex05 - Correta - Questão 10","status":"failed","title":"ex05 - Correta - Questão 10","duration":2.092489999999998,"failureMessages":["AssertionError: expected false to be true // Object.is equality\n    at /home/vicmca/CodeProjects/School/materiais/atividades/2c-revisao-01/ex05.test.js:17:29\n    at file:///home/vicmca/CodeProjects/School/materiais/atividades/2c-revisao-01/node_modules/@vitest/runner/dist/index.js:145:11\n    at file:///home/vicmca/CodeProjects/School/materiais/atividades/2c-revisao-01/node_modules/@vitest/runner/dist/index.js:915:26\n    at file:///home/vicmca/CodeProjects/School/materiais/atividades/2c-revisao-01/node_modules/@vitest/runner/dist/index.js:1243:20\n    at new Promise (<anonymous>)\n    at runWithTimeout (file:///home/vicmca/CodeProjects/School/materiais/atividades/2c-revisao-01/node_modules/@vitest/runner/dist/index.js:1209:10)\n    at file:///home/vicmca/CodeProjects/School/materiais/atividades/2c-revisao-01/node_modules/@vitest/runner/dist/index.js:1653:37\n    at Traces.$ (file:///home/vicmca/CodeProjects/School/materiais/atividades/2c-revisao-01/node_modules/vitest/dist/chunks/traces.CCmnQaNT.js:142:27)\n    at trace (file:///home/vicmca/CodeProjects/School/materiais/atividades/2c-revisao-01/node_modules/vitest/dist/chunks/test.B8ej_ZHS.js:239:21)\n    at runTest (file:///home/vicmca/CodeProjects/School/materiais/atividades/2c-revisao-01/node_modules/@vitest/runner/dist/index.js:1653:12)"],"meta":{}}],"startTime":1773084907125,"endTime":1773084907179.0925,"status":"failed","message":"","name":"/home/vicmca/CodeProjects/School/materiais/atividades/2c-revisao-01/ex05.test.js"}]}